{
  "id": 12337,
  "url": "https://dodgeball.livejournal.com/12337.html",
  "title": ">>> The ClimaXX AWAITS",
  "date": "",
  "body_text": "The long awaited DODGEBALL 20 poster is finally here. Enjoy all the memories that dodgeball has given us in the past 4 months with this very special collage promotional poster.\nThe ClimaXX is indeed coming ...\nCheck out \"DODGEBALL Promotional Posters\" at\nhttp://community.webshots.com/user/undertaker15yrs\nfor the \"breaking-apart\" of this very poster.",
  "body_html": "<div class=\"aentry-post__text aentry-post__text--view\"> The long awaited DODGEBALL 20 poster is finally here. Enjoy all the memories that dodgeball has given us in the past 4 months with this very special collage promotional poster.<br/><br/>The ClimaXX is indeed coming ...<br/><br/><center><img alt=\"Image hosted by Photobucket.com\" fetchpriority=\"high\" src=\"https://i9.photobucket.com/albums/a86/wwecoowner/DODGEBALL%20POSTERS/D20PromoC1FullDesign.jpg\"/></center><br/>Check out \"DODGEBALL Promotional Posters\" at <a href=\"http://community.webshots.com/user/undertaker15yrs\" rel=\"nofollow\" target=\"_blank\">http://community.webshots.com/user/undertaker15yrs</a> for the \"breaking-apart\" of this very poster. </div>",
  "comment_count_text": "",
  "images": [
    "https://i9.photobucket.com/albums/a86/wwecoowner/DODGEBALL%20POSTERS/D20PromoC1FullDesign.jpg"
  ],
  "tags": [],
  "source": "requests_bs4"
}