{
  "id": 87039,
  "url": "https://dodgeball.livejournal.com/87039.html",
  "title": "Way Too Many LETTERS",
  "date": "",
  "body_text": "Letters, like the alphabet? Something's up.\nDODGEBALL CXXXVI - the 136th - crashes the Wall High School tennis courts for yet another action-packed, three-hour massacre presented by\nEastCoastDodgeball\n. The main attraction for this spectacular will be announced live on May 3.\nThe is undoubtedly one of the most crucial time periods in the history of the sport, and the Season 14 finale much reason why. Remember, DODGEBALL CXL team generals\nJuan Londono\nand\nJustin Wolf\nwill no longer be allowed to combine their unlimited resources. It should be very interesting to see what happens during this time. But you won't know unless you show.",
  "body_html": "<div class=\"aentry-post__text aentry-post__text--view\"> Letters, like the alphabet? Something's up.<br/><br/>DODGEBALL CXXXVI - the 136th - crashes the Wall High School tennis courts for yet another action-packed, three-hour massacre presented by <i>EastCoastDodgeball</i>. The main attraction for this spectacular will be announced live on May 3.<br/><br/>The is undoubtedly one of the most crucial time periods in the history of the sport, and the Season 14 finale much reason why. Remember, DODGEBALL CXL team generals <b>Juan Londono</b> and <b>Justin Wolf</b> will no longer be allowed to combine their unlimited resources. It should be very interesting to see what happens during this time. But you won't know unless you show. </div>",
  "comment_count_text": "",
  "images": [],
  "tags": [],
  "source": "requests_bs4"
}