[
  {
    "year": 2004,
    "milestone": "Life-altering car accident resulting in panic attacks and anxiety",
    "sentiment_polarity": 0.0,
    "sentiment_subjectivity": 0.0,
    "category": "vehicle",
    "vader_compound": -0.875,
    "vader_pos": 0.0,
    "vader_neg": 0.688,
    "sentiment_adjusted": -0.875,
    "topic": "Topic 7: aug, 16, dodgeball, 21",
    "life_stage": "Ordinary World"
  },
  {
    "year": 2004,
    "milestone": "Timeline project begins on LiveJournal (Jul 29)",
    "sentiment_polarity": 0.0,
    "sentiment_subjectivity": 0.0,
    "category": "other",
    "vader_compound": 0.0,
    "vader_pos": 0.0,
    "vader_neg": 0.0,
    "sentiment_adjusted": 0.0,
    "topic": "Topic 8: jul, 29, birthday, married",
    "life_stage": "Ordinary World"
  },
  {
    "year": 2005,
    "milestone": "Difficult period after WrestleMania attendance",
    "sentiment_polarity": -0.5,
    "sentiment_subjectivity": 1.0,
    "category": "wwe",
    "vader_compound": -0.361,
    "vader_pos": 0.0,
    "vader_neg": 0.385,
    "sentiment_adjusted": -0.311,
    "topic": "Topic 7: aug, 16, dodgeball, 21",
    "life_stage": "Ordinary World"
  },
  {
    "year": 2005,
    "milestone": "EastCoastDodgeball founded",
    "sentiment_polarity": 0.0,
    "sentiment_subjectivity": 0.0,
    "category": "ecd",
    "vader_compound": 0.0,
    "vader_pos": 0.0,
    "vader_neg": 0.0,
    "sentiment_adjusted": 0.0,
    "topic": "Topic 1: sep, 27, turned, birthday",
    "life_stage": "Ordinary World"
  },
  {
    "year": 2006,
    "milestone": "DODGEBALL 70 (Dec 30) \u2014 music experiment with dance anthems",
    "sentiment_polarity": 0.0,
    "sentiment_subjectivity": 0.0,
    "category": "ecd",
    "vader_compound": 0.0,
    "vader_pos": 0.0,
    "vader_neg": 0.0,
    "sentiment_adjusted": 0.0,
    "topic": "Topic 5: dec, 15, 18, 12",
    "life_stage": "Ordinary World"
  },
  {
    "year": 2006,
    "milestone": "FINS Friday gatherings ongoing since March 2006",
    "sentiment_polarity": 0.0,
    "sentiment_subjectivity": 0.0,
    "category": "other",
    "vader_compound": 0.0,
    "vader_pos": 0.0,
    "vader_neg": 0.0,
    "sentiment_adjusted": 0.0,
    "topic": "Topic 3: trip, ski, 000, road",
    "life_stage": "Ordinary World"
  },
  {
    "year": 2007,
    "milestone": "20+ hours of tennis in one week",
    "sentiment_polarity": 0.0,
    "sentiment_subjectivity": 0.0,
    "category": "sports",
    "vader_compound": 0.0,
    "vader_pos": 0.0,
    "vader_neg": 0.0,
    "sentiment_adjusted": 0.0,
    "topic": "Topic 5: dec, 15, 18, 12",
    "life_stage": "Call to Adventure"
  },
  {
    "year": 2007,
    "milestone": "27 bowling games in a single day",
    "sentiment_polarity": -0.071,
    "sentiment_subjectivity": 0.214,
    "category": "sports",
    "vader_compound": 0.0,
    "vader_pos": 0.0,
    "vader_neg": 0.0,
    "sentiment_adjusted": 0.0,
    "topic": "Topic 1: sep, 27, turned, birthday",
    "life_stage": "Call to Adventure"
  },
  {
    "year": 2007,
    "milestone": "51st WWE event (Oct 29 Philadelphia)",
    "sentiment_polarity": 0.0,
    "sentiment_subjectivity": 0.0,
    "category": "wwe",
    "vader_compound": 0.0,
    "vader_pos": 0.0,
    "vader_neg": 0.0,
    "sentiment_adjusted": 0.05,
    "topic": "Topic 6: wwe, event, oct, mar",
    "life_stage": "Call to Adventure"
  },
  {
    "year": 2007,
    "milestone": "Contracted Shingles at age 20",
    "sentiment_polarity": 0.0,
    "sentiment_subjectivity": 0.0,
    "category": "health",
    "vader_compound": 0.0,
    "vader_pos": 0.0,
    "vader_neg": 0.0,
    "sentiment_adjusted": -0.1,
    "topic": "Topic 7: aug, 16, dodgeball, 21",
    "life_stage": "Call to Adventure"
  },
  {
    "year": 2007,
    "milestone": "Crazy Chili Dog post: dense esoteric reflection on reconciliation, Team Paul (Bobbo + Jimmy), and personal growth. 'My oh my, how the times have changed.'",
    "sentiment_polarity": 0.15,
    "sentiment_subjectivity": 0.6,
    "category": "writing",
    "vader_compound": 0.052,
    "vader_pos": 0.096,
    "vader_neg": 0.089,
    "sentiment_adjusted": 0.052,
    "topic": "Topic 2: year, comedian, anniversary, ecd",
    "life_stage": "Call to Adventure"
  },
  {
    "year": 2007,
    "milestone": "DODGEBALL 100 \u2014 record 52 participants (Aug 18)",
    "sentiment_polarity": 0.0,
    "sentiment_subjectivity": 0.0,
    "category": "ecd",
    "vader_compound": 0.2,
    "vader_pos": 0.0,
    "vader_neg": 0.0,
    "sentiment_adjusted": 0.3,
    "topic": "Topic 7: aug, 16, dodgeball, 21",
    "life_stage": "Call to Adventure"
  },
  {
    "year": 2007,
    "milestone": "Dad's surprise 50th birthday (Jul 29)",
    "sentiment_polarity": 0.0,
    "sentiment_subjectivity": 0.0,
    "category": "family",
    "vader_compound": 0.273,
    "vader_pos": 0.296,
    "vader_neg": 0.0,
    "sentiment_adjusted": 0.273,
    "topic": "Topic 8: jul, 29, birthday, married",
    "life_stage": "Call to Adventure"
  },
  {
    "year": 2007,
    "milestone": "Lauren Winston turned 21 (Apr 13)",
    "sentiment_polarity": 0.0,
    "sentiment_subjectivity": 0.0,
    "category": "other",
    "vader_compound": 0.0,
    "vader_pos": 0.0,
    "vader_neg": 0.0,
    "sentiment_adjusted": 0.0,
    "topic": "Topic 7: aug, 16, dodgeball, 21",
    "life_stage": "Call to Adventure"
  },
  {
    "year": 2007,
    "milestone": "MU Co-Ed Dodgeball League championship (Nov 19, PondScum)",
    "sentiment_polarity": 0.0,
    "sentiment_subjectivity": 0.0,
    "category": "ecd",
    "vader_compound": 0.44,
    "vader_pos": 0.293,
    "vader_neg": 0.0,
    "sentiment_adjusted": 0.54,
    "topic": "Topic 7: aug, 16, dodgeball, 21",
    "life_stage": "Call to Adventure"
  },
  {
    "year": 2007,
    "milestone": "Moved back to Mom's permanently (Jul 1)",
    "sentiment_polarity": 0.0,
    "sentiment_subjectivity": 0.0,
    "category": "family",
    "vader_compound": 0.0,
    "vader_pos": 0.0,
    "vader_neg": 0.0,
    "sentiment_adjusted": 0.0,
    "topic": "Topic 8: jul, 29, birthday, married",
    "life_stage": "Call to Adventure"
  },
  {
    "year": 2007,
    "milestone": "Started job at Ocean Township Recreation (Feb 27)",
    "sentiment_polarity": 0.0,
    "sentiment_subjectivity": 0.0,
    "category": "career",
    "vader_compound": 0.0,
    "vader_pos": 0.0,
    "vader_neg": 0.0,
    "sentiment_adjusted": 0.0,
    "topic": "Topic 1: sep, 27, turned, birthday",
    "life_stage": "Call to Adventure"
  },
  {
    "year": 2007,
    "milestone": "Turned 23 (Sep 27)",
    "sentiment_polarity": 0.0,
    "sentiment_subjectivity": 0.0,
    "category": "other",
    "vader_compound": 0.0,
    "vader_pos": 0.0,
    "vader_neg": 0.0,
    "sentiment_adjusted": 0.0,
    "topic": "Topic 1: sep, 27, turned, birthday",
    "life_stage": "Call to Adventure"
  },
  {
    "year": 2007,
    "milestone": "WWE Stock purchased (Dec 12)",
    "sentiment_polarity": 0.0,
    "sentiment_subjectivity": 0.0,
    "category": "wwe",
    "vader_compound": 0.0,
    "vader_pos": 0.0,
    "vader_neg": 0.0,
    "sentiment_adjusted": 0.05,
    "topic": "Topic 5: dec, 15, 18, 12",
    "life_stage": "Call to Adventure"
  },
  {
    "year": 2007,
    "milestone": "WrestleMania 23 in Detroit (3rd WM)",
    "sentiment_polarity": 0.0,
    "sentiment_subjectivity": 0.0,
    "category": "wwe",
    "vader_compound": 0.0,
    "vader_pos": 0.0,
    "vader_neg": 0.0,
    "sentiment_adjusted": 0.05,
    "topic": "Topic 8: jul, 29, birthday, married",
    "life_stage": "Call to Adventure"
  },
  {
    "year": 2008,
    "milestone": "Came out in 2008; KMJ was 3rd person to know",
    "sentiment_polarity": 0.0,
    "sentiment_subjectivity": 0.0,
    "category": "personal",
    "vader_compound": 0.0,
    "vader_pos": 0.0,
    "vader_neg": 0.0,
    "sentiment_adjusted": 0.0,
    "topic": "Topic 8: jul, 29, birthday, married",
    "life_stage": "Crossing the Threshold"
  },
  {
    "year": 2008,
    "milestone": "Car accident on West Park Avenue (Nov 4)",
    "sentiment_polarity": 0.0,
    "sentiment_subjectivity": 0.0,
    "category": "relationship",
    "vader_compound": -0.477,
    "vader_pos": 0.0,
    "vader_neg": 0.307,
    "sentiment_adjusted": -0.477,
    "topic": "Topic 7: aug, 16, dodgeball, 21",
    "life_stage": "Crossing the Threshold"
  },
  {
    "year": 2008,
    "milestone": "DODGEBALL 150 (Aug 9)",
    "sentiment_polarity": 0.0,
    "sentiment_subjectivity": 0.0,
    "category": "ecd",
    "vader_compound": 0.0,
    "vader_pos": 0.0,
    "vader_neg": 0.0,
    "sentiment_adjusted": 0.0,
    "topic": "Topic 7: aug, 16, dodgeball, 21",
    "life_stage": "Crossing the Threshold"
  },
  {
    "year": 2008,
    "milestone": "Deactivated Facebook after 4-hour paper incident",
    "sentiment_polarity": 0.0,
    "sentiment_subjectivity": 0.0,
    "category": "personal",
    "vader_compound": 0.0,
    "vader_pos": 0.0,
    "vader_neg": 0.0,
    "sentiment_adjusted": 0.0,
    "topic": "Topic 1: sep, 27, turned, birthday",
    "life_stage": "Crossing the Threshold"
  },
  {
    "year": 2008,
    "milestone": "Diana DiBuccio: Comedian of the Year",
    "sentiment_polarity": 0.0,
    "sentiment_subjectivity": 0.0,
    "category": "music_awards",
    "vader_compound": 0.382,
    "vader_pos": 0.342,
    "vader_neg": 0.0,
    "sentiment_adjusted": 0.382,
    "topic": "Topic 2: year, comedian, anniversary, ecd",
    "life_stage": "Crossing the Threshold"
  },
  {
    "year": 2008,
    "milestone": "ECD 3-Year Anniversary (Sep 6)",
    "sentiment_polarity": 0.0,
    "sentiment_subjectivity": 0.0,
    "category": "ecd",
    "vader_compound": 0.0,
    "vader_pos": 0.0,
    "vader_neg": 0.0,
    "sentiment_adjusted": 0.0,
    "topic": "Topic 2: year, comedian, anniversary, ecd",
    "life_stage": "Crossing the Threshold"
  },
  {
    "year": 2008,
    "milestone": "FAB4 Atlantic City trips began",
    "sentiment_polarity": 0.0,
    "sentiment_subjectivity": 0.0,
    "category": "travel",
    "vader_compound": 0.0,
    "vader_pos": 0.0,
    "vader_neg": 0.0,
    "sentiment_adjusted": 0.05,
    "topic": "Topic 5: dec, 15, 18, 12",
    "life_stage": "Crossing the Threshold"
  },
  {
    "year": 2008,
    "milestone": "First beer shared with The Pops (Aug 21)",
    "sentiment_polarity": 0.25,
    "sentiment_subjectivity": 0.333,
    "category": "family",
    "vader_compound": 0.34,
    "vader_pos": 0.255,
    "vader_neg": 0.0,
    "sentiment_adjusted": 0.34,
    "topic": "Topic 7: aug, 16, dodgeball, 21",
    "life_stage": "Crossing the Threshold"
  },
  {
    "year": 2008,
    "milestone": "First semester of Health Studies completed at MU (May 8)",
    "sentiment_polarity": 0.375,
    "sentiment_subjectivity": 0.667,
    "category": "education",
    "vader_compound": 0.44,
    "vader_pos": 0.244,
    "vader_neg": 0.0,
    "sentiment_adjusted": 0.44,
    "topic": "Topic 5: dec, 15, 18, 12",
    "life_stage": "Crossing the Threshold"
  },
  {
    "year": 2008,
    "milestone": "Royal Rumble at MSG (Jan 27)",
    "sentiment_polarity": 0.0,
    "sentiment_subjectivity": 0.0,
    "category": "wwe",
    "vader_compound": 0.0,
    "vader_pos": 0.0,
    "vader_neg": 0.0,
    "sentiment_adjusted": 0.05,
    "topic": "Topic 1: sep, 27, turned, birthday",
    "life_stage": "Crossing the Threshold"
  },
  {
    "year": 2008,
    "milestone": "Song of the Year: Tom Petty 'Runnin Down a Dream'",
    "sentiment_polarity": -0.156,
    "sentiment_subjectivity": 0.289,
    "category": "music_awards",
    "vader_compound": 0.052,
    "vader_pos": 0.185,
    "vader_neg": 0.167,
    "sentiment_adjusted": 0.052,
    "topic": "Topic 2: year, comedian, anniversary, ecd",
    "life_stage": "Crossing the Threshold"
  },
  {
    "year": 2008,
    "milestone": "Turned 24 (Sep 27)",
    "sentiment_polarity": 0.0,
    "sentiment_subjectivity": 0.0,
    "category": "other",
    "vader_compound": 0.0,
    "vader_pos": 0.0,
    "vader_neg": 0.0,
    "sentiment_adjusted": 0.0,
    "topic": "Topic 1: sep, 27, turned, birthday",
    "life_stage": "Crossing the Threshold"
  },
  {
    "year": 2008,
    "milestone": "WrestleMania XXIV in Florida (4th WM)",
    "sentiment_polarity": 0.0,
    "sentiment_subjectivity": 0.0,
    "category": "wwe",
    "vader_compound": 0.0,
    "vader_pos": 0.0,
    "vader_neg": 0.0,
    "sentiment_adjusted": 0.05,
    "topic": "Topic 7: aug, 16, dodgeball, 21",
    "life_stage": "Crossing the Threshold"
  },
  {
    "year": 2008,
    "milestone": "Yeah I Said It post: raw honest reflection. Reveals 2004 car accident caused panic attacks, 2005 near-anorexia. Letsche friendship repaired at Rumble '08. First appearance of 'The power of an internal desire liberated!' \u2014 March 2008.",
    "sentiment_polarity": 0.25,
    "sentiment_subjectivity": 0.7,
    "category": "personal",
    "vader_compound": 0.271,
    "vader_pos": 0.239,
    "vader_neg": 0.195,
    "sentiment_adjusted": 0.271,
    "topic": "Topic 3: trip, ski, 000, road",
    "life_stage": "Crossing the Threshold"
  },
  {
    "year": 2009,
    "milestone": "'The Greatest Year Ever. 2009.'",
    "sentiment_polarity": 1.0,
    "sentiment_subjectivity": 1.0,
    "category": "other",
    "vader_compound": 0.637,
    "vader_pos": 0.512,
    "vader_neg": 0.0,
    "sentiment_adjusted": 0.637,
    "topic": "Topic 2: year, comedian, anniversary, ecd",
    "life_stage": "Tests, Allies & Enemies"
  },
  {
    "year": 2009,
    "milestone": "28 beers consumed all year; 101 dates posted; 0 regrets",
    "sentiment_polarity": -0.1,
    "sentiment_subjectivity": 0.2,
    "category": "other",
    "vader_compound": -0.361,
    "vader_pos": 0.0,
    "vader_neg": 0.238,
    "sentiment_adjusted": -0.361,
    "topic": "Topic 2: year, comedian, anniversary, ecd",
    "life_stage": "Tests, Allies & Enemies"
  },
  {
    "year": 2009,
    "milestone": "62nd WWE event (Hell In A Cell Oct 4)",
    "sentiment_polarity": 0.0,
    "sentiment_subjectivity": 0.0,
    "category": "wwe",
    "vader_compound": 0.0,
    "vader_pos": 0.0,
    "vader_neg": 0.0,
    "sentiment_adjusted": 0.05,
    "topic": "Topic 6: wwe, event, oct, mar",
    "life_stage": "Tests, Allies & Enemies"
  },
  {
    "year": 2009,
    "milestone": "Bowling 255 during a snowstorm (Mar 1)",
    "sentiment_polarity": 0.0,
    "sentiment_subjectivity": 0.0,
    "category": "sports",
    "vader_compound": 0.0,
    "vader_pos": 0.0,
    "vader_neg": 0.0,
    "sentiment_adjusted": 0.0,
    "topic": "Topic 6: wwe, event, oct, mar",
    "life_stage": "Tests, Allies & Enemies"
  },
  {
    "year": 2009,
    "milestone": "First concert ever: John Legend at MSG with Kanye West (Aug 13)",
    "sentiment_polarity": 0.25,
    "sentiment_subjectivity": 0.333,
    "category": "entertainment",
    "vader_compound": 0.0,
    "vader_pos": 0.0,
    "vader_neg": 0.0,
    "sentiment_adjusted": 0.0,
    "topic": "Topic 7: aug, 16, dodgeball, 21",
    "life_stage": "Tests, Allies & Enemies"
  },
  {
    "year": 2009,
    "milestone": "Grandmother's 77th birthday (Nov 13)",
    "sentiment_polarity": 0.0,
    "sentiment_subjectivity": 0.0,
    "category": "family",
    "vader_compound": 0.0,
    "vader_pos": 0.0,
    "vader_neg": 0.0,
    "sentiment_adjusted": 0.0,
    "topic": "Topic 8: jul, 29, birthday, married",
    "life_stage": "Tests, Allies & Enemies"
  },
  {
    "year": 2009,
    "milestone": "Inducted into Eta Sigma Gamma at MU (Dec 16)",
    "sentiment_polarity": 0.0,
    "sentiment_subjectivity": 0.0,
    "category": "family",
    "vader_compound": 0.0,
    "vader_pos": 0.0,
    "vader_neg": 0.0,
    "sentiment_adjusted": 0.0,
    "topic": "Topic 5: dec, 15, 18, 12",
    "life_stage": "Tests, Allies & Enemies"
  },
  {
    "year": 2009,
    "milestone": "Retired from ECD after 171 events and 40 months (Jan 3)",
    "sentiment_polarity": 0.0,
    "sentiment_subjectivity": 0.0,
    "category": "ecd",
    "vader_compound": 0.0,
    "vader_pos": 0.0,
    "vader_neg": 0.0,
    "sentiment_adjusted": 0.0,
    "topic": "Topic 2: year, comedian, anniversary, ecd",
    "life_stage": "Tests, Allies & Enemies"
  },
  {
    "year": 2009,
    "milestone": "SkyDive I at 10,000 feet (Aug 16) \u2014 'maybe the happiest 24-span of my life'",
    "sentiment_polarity": 0.0,
    "sentiment_subjectivity": 0.0,
    "category": "sports",
    "vader_compound": 0.637,
    "vader_pos": 0.259,
    "vader_neg": 0.0,
    "sentiment_adjusted": 0.637,
    "topic": "Topic 7: aug, 16, dodgeball, 21",
    "life_stage": "Tests, Allies & Enemies"
  },
  {
    "year": 2009,
    "milestone": "SkyDive II 'Cloud Nine' with 9 people (Oct 11)",
    "sentiment_polarity": 0.0,
    "sentiment_subjectivity": 0.0,
    "category": "sports",
    "vader_compound": 0.0,
    "vader_pos": 0.0,
    "vader_neg": 0.0,
    "sentiment_adjusted": 0.0,
    "topic": "Topic 6: wwe, event, oct, mar",
    "life_stage": "Tests, Allies & Enemies"
  },
  {
    "year": 2009,
    "milestone": "Turned 25 \u2014 multi-day celebration (Sep 25-27)",
    "sentiment_polarity": 0.0,
    "sentiment_subjectivity": 0.0,
    "category": "other",
    "vader_compound": 0.0,
    "vader_pos": 0.0,
    "vader_neg": 0.0,
    "sentiment_adjusted": 0.0,
    "topic": "Topic 1: sep, 27, turned, birthday",
    "life_stage": "Tests, Allies & Enemies"
  },
  {
    "year": 2009,
    "milestone": "U.S. Open Tennis Championships attended (Sep 7)",
    "sentiment_polarity": 0.0,
    "sentiment_subjectivity": 0.5,
    "category": "sports",
    "vader_compound": 0.494,
    "vader_pos": 0.348,
    "vader_neg": 0.0,
    "sentiment_adjusted": 0.594,
    "topic": "Topic 1: sep, 27, turned, birthday",
    "life_stage": "Tests, Allies & Enemies"
  },
  {
    "year": 2009,
    "milestone": "WinterBall with Melissa Kerr (Feb 21)",
    "sentiment_polarity": 0.0,
    "sentiment_subjectivity": 0.0,
    "category": "other",
    "vader_compound": 0.0,
    "vader_pos": 0.0,
    "vader_neg": 0.0,
    "sentiment_adjusted": 0.0,
    "topic": "Topic 7: aug, 16, dodgeball, 21",
    "life_stage": "Tests, Allies & Enemies"
  },
  {
    "year": 2009,
    "milestone": "WrestleMania 25 in Houston (5th WM) \u2014 72,744 attendance",
    "sentiment_polarity": 0.0,
    "sentiment_subjectivity": 0.0,
    "category": "wwe",
    "vader_compound": 0.0,
    "vader_pos": 0.0,
    "vader_neg": 0.0,
    "sentiment_adjusted": 0.05,
    "topic": "Topic 7: aug, 16, dodgeball, 21",
    "life_stage": "Tests, Allies & Enemies"
  },
  {
    "year": 2010,
    "milestone": "18 lbs gained, 3 alcoholic beverages, 0 regrets",
    "sentiment_polarity": -0.175,
    "sentiment_subjectivity": 0.35,
    "category": "other",
    "vader_compound": 0.026,
    "vader_pos": 0.286,
    "vader_neg": 0.275,
    "sentiment_adjusted": 0.026,
    "topic": "Topic 5: dec, 15, 18, 12",
    "life_stage": "Tests, Allies & Enemies"
  },
  {
    "year": 2010,
    "milestone": "3rd skydive (Jul 18)",
    "sentiment_polarity": 0.0,
    "sentiment_subjectivity": 0.0,
    "category": "sports",
    "vader_compound": 0.0,
    "vader_pos": 0.0,
    "vader_neg": 0.0,
    "sentiment_adjusted": 0.0,
    "topic": "Topic 8: jul, 29, birthday, married",
    "life_stage": "Tests, Allies & Enemies"
  },
  {
    "year": 2010,
    "milestone": "Brother Michael graduated from Kean University (May 13)",
    "sentiment_polarity": 0.0,
    "sentiment_subjectivity": 0.0,
    "category": "family",
    "vader_compound": 0.2,
    "vader_pos": 0.0,
    "vader_neg": 0.0,
    "sentiment_adjusted": 0.3,
    "topic": "Topic 8: jul, 29, birthday, married",
    "life_stage": "Tests, Allies & Enemies"
  },
  {
    "year": 2010,
    "milestone": "ECD 5th Year Anniversary (Sep 11)",
    "sentiment_polarity": 0.0,
    "sentiment_subjectivity": 0.0,
    "category": "ecd",
    "vader_compound": 0.0,
    "vader_pos": 0.0,
    "vader_neg": 0.0,
    "sentiment_adjusted": 0.0,
    "topic": "Topic 2: year, comedian, anniversary, ecd",
    "life_stage": "Tests, Allies & Enemies"
  },
  {
    "year": 2010,
    "milestone": "Featured in Phillies PSA (Jun 10)",
    "sentiment_polarity": 0.0,
    "sentiment_subjectivity": 0.0,
    "category": "other",
    "vader_compound": 0.0,
    "vader_pos": 0.0,
    "vader_neg": 0.0,
    "sentiment_adjusted": 0.0,
    "topic": "Topic 7: aug, 16, dodgeball, 21",
    "life_stage": "Tests, Allies & Enemies"
  },
  {
    "year": 2010,
    "milestone": "Graduated Monmouth University (3.66 major GPA, 3.49 cumulative)",
    "sentiment_polarity": 0.062,
    "sentiment_subjectivity": 0.5,
    "category": "education",
    "vader_compound": 0.2,
    "vader_pos": 0.0,
    "vader_neg": 0.0,
    "sentiment_adjusted": 0.3,
    "topic": "Topic 7: aug, 16, dodgeball, 21",
    "life_stage": "Tests, Allies & Enemies"
  },
  {
    "year": 2010,
    "milestone": "HERO Campaign 10th Anniversary at Trump Taj Mahal (Jul 22)",
    "sentiment_polarity": 0.0,
    "sentiment_subjectivity": 0.0,
    "category": "relationship",
    "vader_compound": 0.652,
    "vader_pos": 0.325,
    "vader_neg": 0.0,
    "sentiment_adjusted": 0.652,
    "topic": "Topic 8: jul, 29, birthday, married",
    "life_stage": "Tests, Allies & Enemies"
  },
  {
    "year": 2010,
    "milestone": "Tennis match vs Farnkopf: 6 hours 7 minutes 3 seconds (Sep 21)",
    "sentiment_polarity": 0.0,
    "sentiment_subjectivity": 0.0,
    "category": "sports",
    "vader_compound": 0.0,
    "vader_pos": 0.0,
    "vader_neg": 0.0,
    "sentiment_adjusted": 0.0,
    "topic": "Topic 1: sep, 27, turned, birthday",
    "life_stage": "Tests, Allies & Enemies"
  },
  {
    "year": 2010,
    "milestone": "Won inaugural HERO of the Year (Jan 27)",
    "sentiment_polarity": 0.0,
    "sentiment_subjectivity": 0.0,
    "category": "other",
    "vader_compound": 0.842,
    "vader_pos": 0.572,
    "vader_neg": 0.0,
    "sentiment_adjusted": 0.942,
    "topic": "Topic 2: year, comedian, anniversary, ecd",
    "life_stage": "Tests, Allies & Enemies"
  },
  {
    "year": 2010,
    "milestone": "WrestleMania XXVI in Arizona (939 photos)",
    "sentiment_polarity": 0.0,
    "sentiment_subjectivity": 0.0,
    "category": "wwe",
    "vader_compound": 0.0,
    "vader_pos": 0.0,
    "vader_neg": 0.0,
    "sentiment_adjusted": 0.05,
    "topic": "Topic 3: trip, ski, 000, road",
    "life_stage": "Tests, Allies & Enemies"
  },
  {
    "year": 2011,
    "milestone": "4th consecutive WinterBall (Feb 19)",
    "sentiment_polarity": 0.0,
    "sentiment_subjectivity": 0.0,
    "category": "other",
    "vader_compound": 0.0,
    "vader_pos": 0.0,
    "vader_neg": 0.0,
    "sentiment_adjusted": 0.0,
    "topic": "Topic 6: wwe, event, oct, mar",
    "life_stage": "Tests, Allies & Enemies"
  },
  {
    "year": 2011,
    "milestone": "Career at Sunrise Senior Living begins (Oct 31/Nov 1)",
    "sentiment_polarity": 0.0,
    "sentiment_subjectivity": 0.0,
    "category": "career",
    "vader_compound": 0.0,
    "vader_pos": 0.0,
    "vader_neg": 0.0,
    "sentiment_adjusted": 0.0,
    "topic": "Topic 6: wwe, event, oct, mar",
    "life_stage": "Tests, Allies & Enemies"
  },
  {
    "year": 2011,
    "milestone": "Cousin Nick married Samantha (Jul 2-3)",
    "sentiment_polarity": 0.25,
    "sentiment_subjectivity": 0.25,
    "category": "family",
    "vader_compound": 0.0,
    "vader_pos": 0.0,
    "vader_neg": 0.0,
    "sentiment_adjusted": 0.0,
    "topic": "Topic 8: jul, 29, birthday, married",
    "life_stage": "Tests, Allies & Enemies"
  },
  {
    "year": 2011,
    "milestone": "ECDElite Hall of Fame induction (Jun 18)",
    "sentiment_polarity": 0.0,
    "sentiment_subjectivity": 0.0,
    "category": "wwe",
    "vader_compound": 0.44,
    "vader_pos": 0.326,
    "vader_neg": 0.0,
    "sentiment_adjusted": 0.49,
    "topic": "Topic 5: dec, 15, 18, 12",
    "life_stage": "Tests, Allies & Enemies"
  },
  {
    "year": 2011,
    "milestone": "Fell from a pickup truck (May 21)",
    "sentiment_polarity": 0.0,
    "sentiment_subjectivity": 0.0,
    "category": "other",
    "vader_compound": 0.0,
    "vader_pos": 0.0,
    "vader_neg": 0.0,
    "sentiment_adjusted": 0.0,
    "topic": "Topic 7: aug, 16, dodgeball, 21",
    "life_stage": "Tests, Allies & Enemies"
  },
  {
    "year": 2011,
    "milestone": "First meal with Rob at Ocean Bay Diner (Jan 1)",
    "sentiment_polarity": 0.25,
    "sentiment_subjectivity": 0.333,
    "category": "relationship",
    "vader_compound": -0.557,
    "vader_pos": 0.0,
    "vader_neg": 0.286,
    "sentiment_adjusted": 0.3,
    "topic": "Topic 2: year, comedian, anniversary, ecd",
    "life_stage": "Tests, Allies & Enemies"
  },
  {
    "year": 2011,
    "milestone": "First speeding ticket (Sep 14)",
    "sentiment_polarity": 0.25,
    "sentiment_subjectivity": 0.333,
    "category": "personal",
    "vader_compound": 0.0,
    "vader_pos": 0.0,
    "vader_neg": 0.0,
    "sentiment_adjusted": 0.0,
    "topic": "Topic 1: sep, 27, turned, birthday",
    "life_stage": "Tests, Allies & Enemies"
  },
  {
    "year": 2011,
    "milestone": "Hurricane Irene \u2014 La Quinta Suites (Aug 27-28)",
    "sentiment_polarity": 0.0,
    "sentiment_subjectivity": 0.0,
    "category": "other",
    "vader_compound": 0.0,
    "vader_pos": 0.0,
    "vader_neg": 0.0,
    "sentiment_adjusted": 0.0,
    "topic": "Topic 7: aug, 16, dodgeball, 21",
    "life_stage": "Tests, Allies & Enemies"
  },
  {
    "year": 2011,
    "milestone": "RK's 22nd birthday (Dec 14)",
    "sentiment_polarity": 0.0,
    "sentiment_subjectivity": 0.0,
    "category": "relationship",
    "vader_compound": 0.0,
    "vader_pos": 0.0,
    "vader_neg": 0.0,
    "sentiment_adjusted": 0.0,
    "topic": "Topic 5: dec, 15, 18, 12",
    "life_stage": "Tests, Allies & Enemies"
  },
  {
    "year": 2011,
    "milestone": "Relationship begins Jan 15 (the 'Ro(b)mantic Era')",
    "sentiment_polarity": 0.0,
    "sentiment_subjectivity": 0.0,
    "category": "relationship",
    "vader_compound": 0.0,
    "vader_pos": 0.0,
    "vader_neg": 0.0,
    "sentiment_adjusted": 0.0,
    "topic": "Topic 5: dec, 15, 18, 12",
    "life_stage": "Tests, Allies & Enemies"
  },
  {
    "year": 2011,
    "milestone": "Survivor Series at MSG \u2014 The Rock returns (Nov 20)",
    "sentiment_polarity": 0.0,
    "sentiment_subjectivity": 0.0,
    "category": "wwe",
    "vader_compound": 0.361,
    "vader_pos": 0.238,
    "vader_neg": 0.0,
    "sentiment_adjusted": 0.411,
    "topic": "Topic 7: aug, 16, dodgeball, 21",
    "life_stage": "Tests, Allies & Enemies"
  },
  {
    "year": 2011,
    "milestone": "Torn glenoid labrum confirmed via MRI (Aug 2)",
    "sentiment_polarity": 0.4,
    "sentiment_subjectivity": 1.0,
    "category": "health",
    "vader_compound": -0.25,
    "vader_pos": 0.0,
    "vader_neg": 0.222,
    "sentiment_adjusted": -0.35,
    "topic": "Topic 7: aug, 16, dodgeball, 21",
    "life_stage": "Tests, Allies & Enemies"
  },
  {
    "year": 2012,
    "milestone": "71st WWE event",
    "sentiment_polarity": 0.0,
    "sentiment_subjectivity": 0.0,
    "category": "wwe",
    "vader_compound": 0.0,
    "vader_pos": 0.0,
    "vader_neg": 0.0,
    "sentiment_adjusted": 0.05,
    "topic": "Topic 6: wwe, event, oct, mar",
    "life_stage": "Approach to Inmost Cave"
  },
  {
    "year": 2012,
    "milestone": "Activities & Volunteer Coordinator promotion (May)",
    "sentiment_polarity": 0.0,
    "sentiment_subjectivity": 0.0,
    "category": "career",
    "vader_compound": 0.0,
    "vader_pos": 0.0,
    "vader_neg": 0.0,
    "sentiment_adjusted": 0.0,
    "topic": "Topic 8: jul, 29, birthday, married",
    "life_stage": "Approach to Inmost Cave"
  },
  {
    "year": 2012,
    "milestone": "ECD 7th birthday + 500th player (Sep 1)",
    "sentiment_polarity": 0.0,
    "sentiment_subjectivity": 0.0,
    "category": "ecd",
    "vader_compound": 0.0,
    "vader_pos": 0.0,
    "vader_neg": 0.0,
    "sentiment_adjusted": 0.0,
    "topic": "Topic 1: sep, 27, turned, birthday",
    "life_stage": "Approach to Inmost Cave"
  },
  {
    "year": 2012,
    "milestone": "ECD reopened with 'WORLD TOUR' (Apr 7)",
    "sentiment_polarity": 0.0,
    "sentiment_subjectivity": 0.0,
    "category": "ecd",
    "vader_compound": 0.0,
    "vader_pos": 0.0,
    "vader_neg": 0.0,
    "sentiment_adjusted": 0.0,
    "topic": "Topic 7: aug, 16, dodgeball, 21",
    "life_stage": "Approach to Inmost Cave"
  },
  {
    "year": 2012,
    "milestone": "Employee of the Month (Jan)",
    "sentiment_polarity": 0.0,
    "sentiment_subjectivity": 0.0,
    "category": "career",
    "vader_compound": 0.0,
    "vader_pos": 0.0,
    "vader_neg": 0.0,
    "sentiment_adjusted": 0.0,
    "topic": "Topic 5: dec, 15, 18, 12",
    "life_stage": "Approach to Inmost Cave"
  },
  {
    "year": 2012,
    "milestone": "Record 18 rounds at Orchard Park (Oct 13)",
    "sentiment_polarity": 0.0,
    "sentiment_subjectivity": 0.0,
    "category": "relationship",
    "vader_compound": 0.2,
    "vader_pos": 0.0,
    "vader_neg": 0.0,
    "sentiment_adjusted": 0.3,
    "topic": "Topic 6: wwe, event, oct, mar",
    "life_stage": "Approach to Inmost Cave"
  },
  {
    "year": 2012,
    "milestone": "SUS15H reached 190,000 miles (Nov)",
    "sentiment_polarity": 0.0,
    "sentiment_subjectivity": 0.0,
    "category": "travel",
    "vader_compound": 0.103,
    "vader_pos": 0.259,
    "vader_neg": 0.0,
    "sentiment_adjusted": 0.153,
    "topic": "Topic 3: trip, ski, 000, road",
    "life_stage": "Approach to Inmost Cave"
  },
  {
    "year": 2012,
    "milestone": "Stratton Vermont ski trip continues",
    "sentiment_polarity": 0.0,
    "sentiment_subjectivity": 0.0,
    "category": "travel",
    "vader_compound": 0.0,
    "vader_pos": 0.0,
    "vader_neg": 0.0,
    "sentiment_adjusted": 0.05,
    "topic": "Topic 3: trip, ski, 000, road",
    "life_stage": "Approach to Inmost Cave"
  },
  {
    "year": 2013,
    "milestone": "'2010 and 2013 will no doubt stand the test of time'",
    "sentiment_polarity": 0.0,
    "sentiment_subjectivity": 0.0,
    "category": "other",
    "vader_compound": -0.572,
    "vader_pos": 0.0,
    "vader_neg": 0.343,
    "sentiment_adjusted": 0.3,
    "topic": "Topic 6: wwe, event, oct, mar",
    "life_stage": "Approach to Inmost Cave"
  },
  {
    "year": 2013,
    "milestone": "'Table 7' Era begins (Jun 8)",
    "sentiment_polarity": 0.5,
    "sentiment_subjectivity": 1.0,
    "category": "other",
    "vader_compound": 0.44,
    "vader_pos": 0.367,
    "vader_neg": 0.0,
    "sentiment_adjusted": 0.44,
    "topic": "Topic 8: jul, 29, birthday, married",
    "life_stage": "Approach to Inmost Cave"
  },
  {
    "year": 2013,
    "milestone": "5 weddings attended in one year",
    "sentiment_polarity": 0.0,
    "sentiment_subjectivity": 0.0,
    "category": "social",
    "vader_compound": 0.0,
    "vader_pos": 0.0,
    "vader_neg": 0.0,
    "sentiment_adjusted": 0.0,
    "topic": "Topic 2: year, comedian, anniversary, ecd",
    "life_stage": "Approach to Inmost Cave"
  },
  {
    "year": 2013,
    "milestone": "5th consecutive VT skiing trip (Jan 6-9)",
    "sentiment_polarity": 0.0,
    "sentiment_subjectivity": 0.0,
    "category": "travel",
    "vader_compound": 0.0,
    "vader_pos": 0.0,
    "vader_neg": 0.0,
    "sentiment_adjusted": 0.05,
    "topic": "Topic 3: trip, ski, 000, road",
    "life_stage": "Approach to Inmost Cave"
  },
  {
    "year": 2013,
    "milestone": "DODGEBOWL 200 \u2014 era-ending extravaganza (Aug 10, FIVE star rating)",
    "sentiment_polarity": 0.0,
    "sentiment_subjectivity": 0.0,
    "category": "ecd",
    "vader_compound": 0.0,
    "vader_pos": 0.0,
    "vader_neg": 0.0,
    "sentiment_adjusted": 0.0,
    "topic": "Topic 7: aug, 16, dodgeball, 21",
    "life_stage": "Approach to Inmost Cave"
  },
  {
    "year": 2013,
    "milestone": "Grandma Theresa passed away (Jun 10-15)",
    "sentiment_polarity": 0.0,
    "sentiment_subjectivity": 0.0,
    "category": "family",
    "vader_compound": 0.0,
    "vader_pos": 0.0,
    "vader_neg": 0.0,
    "sentiment_adjusted": 0.0,
    "topic": "Topic 5: dec, 15, 18, 12",
    "life_stage": "Approach to Inmost Cave"
  },
  {
    "year": 2013,
    "milestone": "Maryland wedding \u2014 gave speech, danced 180 minutes (Nov 7-9)",
    "sentiment_polarity": 0.0,
    "sentiment_subjectivity": 0.0,
    "category": "social",
    "vader_compound": 0.0,
    "vader_pos": 0.0,
    "vader_neg": 0.0,
    "sentiment_adjusted": 0.0,
    "topic": "Topic 3: trip, ski, 000, road",
    "life_stage": "Approach to Inmost Cave"
  },
  {
    "year": 2013,
    "milestone": "Norwegian Breakaway \u2014 first cruise ever, first with RK (Sep 8-15, FIVE star rating)",
    "sentiment_polarity": 0.167,
    "sentiment_subjectivity": 0.222,
    "category": "travel",
    "vader_compound": 0.0,
    "vader_pos": 0.0,
    "vader_neg": 0.0,
    "sentiment_adjusted": 0.05,
    "topic": "Topic 4: cruise, croatia, years, 10",
    "life_stage": "Approach to Inmost Cave"
  },
  {
    "year": 2013,
    "milestone": "Pilates Round 1 \u2014 only male participant",
    "sentiment_polarity": -0.067,
    "sentiment_subjectivity": 0.5,
    "category": "other",
    "vader_compound": 0.0,
    "vader_pos": 0.0,
    "vader_neg": 0.0,
    "sentiment_adjusted": 0.0,
    "topic": "Topic 1: sep, 27, turned, birthday",
    "life_stage": "Approach to Inmost Cave"
  },
  {
    "year": 2013,
    "milestone": "Turned 29 (Sep 27)",
    "sentiment_polarity": 0.0,
    "sentiment_subjectivity": 0.0,
    "category": "other",
    "vader_compound": 0.0,
    "vader_pos": 0.0,
    "vader_neg": 0.0,
    "sentiment_adjusted": 0.0,
    "topic": "Topic 1: sep, 27, turned, birthday",
    "life_stage": "Approach to Inmost Cave"
  },
  {
    "year": 2013,
    "milestone": "WWE event #75 (Sep 3)",
    "sentiment_polarity": 0.0,
    "sentiment_subjectivity": 0.0,
    "category": "wwe",
    "vader_compound": 0.0,
    "vader_pos": 0.0,
    "vader_neg": 0.0,
    "sentiment_adjusted": 0.05,
    "topic": "Topic 6: wwe, event, oct, mar",
    "life_stage": "Approach to Inmost Cave"
  },
  {
    "year": 2013,
    "milestone": "WrestleMania 29 at-home NJ (8th WM); 21-0 record",
    "sentiment_polarity": 0.0,
    "sentiment_subjectivity": 0.0,
    "category": "wwe",
    "vader_compound": 0.2,
    "vader_pos": 0.0,
    "vader_neg": 0.0,
    "sentiment_adjusted": 0.3,
    "topic": "Topic 8: jul, 29, birthday, married",
    "life_stage": "Approach to Inmost Cave"
  },
  {
    "year": 2014,
    "milestone": "Cornhole Championship won with Pops at Maggie & Mike's (Aug 30)",
    "sentiment_polarity": 0.0,
    "sentiment_subjectivity": 0.0,
    "category": "sports",
    "vader_compound": 0.765,
    "vader_pos": 0.452,
    "vader_neg": 0.0,
    "sentiment_adjusted": 0.865,
    "topic": "Topic 7: aug, 16, dodgeball, 21",
    "life_stage": "The Ordeal"
  },
  {
    "year": 2014,
    "milestone": "Diana's 30th, Valerie's 30th, Pam's 30th, author's 30th \u2014 trend of 30s",
    "sentiment_polarity": 0.0,
    "sentiment_subjectivity": 0.0,
    "category": "other",
    "vader_compound": 0.0,
    "vader_pos": 0.0,
    "vader_neg": 0.0,
    "sentiment_adjusted": 0.0,
    "topic": "Topic 5: dec, 15, 18, 12",
    "life_stage": "The Ordeal"
  },
  {
    "year": 2014,
    "milestone": "Gray Kia Soul purchased (Jan 11-13)",
    "sentiment_polarity": 0.0,
    "sentiment_subjectivity": 0.0,
    "category": "vehicle",
    "vader_compound": -0.637,
    "vader_pos": 0.0,
    "vader_neg": 0.457,
    "sentiment_adjusted": 0.15,
    "topic": "Topic 5: dec, 15, 18, 12",
    "life_stage": "The Ordeal"
  },
  {
    "year": 2014,
    "milestone": "Johnny Nash: most influential friend of 2014",
    "sentiment_polarity": 0.5,
    "sentiment_subjectivity": 0.5,
    "category": "other",
    "vader_compound": 0.77,
    "vader_pos": 0.572,
    "vader_neg": 0.0,
    "sentiment_adjusted": 0.77,
    "topic": "Topic 1: sep, 27, turned, birthday",
    "life_stage": "The Ordeal"
  },
  {
    "year": 2014,
    "milestone": "Met The Undertaker at WM XXX (4:10:18 PM CT Apr 5)",
    "sentiment_polarity": 0.0,
    "sentiment_subjectivity": 0.0,
    "category": "wwe",
    "vader_compound": 0.0,
    "vader_pos": 0.0,
    "vader_neg": 0.0,
    "sentiment_adjusted": 0.05,
    "topic": "Topic 7: aug, 16, dodgeball, 21",
    "life_stage": "The Ordeal"
  },
  {
    "year": 2014,
    "milestone": "Moved to Oceanport (Sep 1)",
    "sentiment_polarity": 0.0,
    "sentiment_subjectivity": 0.0,
    "category": "personal",
    "vader_compound": 0.0,
    "vader_pos": 0.0,
    "vader_neg": 0.0,
    "sentiment_adjusted": 0.0,
    "topic": "Topic 1: sep, 27, turned, birthday",
    "life_stage": "The Ordeal"
  },
  {
    "year": 2014,
    "milestone": "Norwegian Epic cruise II \u2014 Jamaica, Grand Cayman, Cozumel (Dec 6-15)",
    "sentiment_polarity": 0.2,
    "sentiment_subjectivity": 0.467,
    "category": "travel",
    "vader_compound": 0.459,
    "vader_pos": 0.25,
    "vader_neg": 0.0,
    "sentiment_adjusted": 0.509,
    "topic": "Topic 5: dec, 15, 18, 12",
    "life_stage": "The Ordeal"
  },
  {
    "year": 2014,
    "milestone": "SUS15H takes its last ride (Dec 24-25)",
    "sentiment_polarity": 0.0,
    "sentiment_subjectivity": 0.067,
    "category": "vehicle",
    "vader_compound": 0.0,
    "vader_pos": 0.0,
    "vader_neg": 0.0,
    "sentiment_adjusted": 0.0,
    "topic": "Topic 5: dec, 15, 18, 12",
    "life_stage": "The Ordeal"
  },
  {
    "year": 2014,
    "milestone": "The Pops: Comedian of the Year (2nd straight year)",
    "sentiment_polarity": 0.1,
    "sentiment_subjectivity": 0.2,
    "category": "family",
    "vader_compound": 0.542,
    "vader_pos": 0.391,
    "vader_neg": 0.0,
    "sentiment_adjusted": 0.542,
    "topic": "Topic 2: year, comedian, anniversary, ecd",
    "life_stage": "The Ordeal"
  },
  {
    "year": 2014,
    "milestone": "Turned 30 \u2014 the 'BIG 3-0'",
    "sentiment_polarity": 0.0,
    "sentiment_subjectivity": 0.1,
    "category": "other",
    "vader_compound": 0.0,
    "vader_pos": 0.0,
    "vader_neg": 0.0,
    "sentiment_adjusted": 0.0,
    "topic": "Topic 1: sep, 27, turned, birthday",
    "life_stage": "The Ordeal"
  },
  {
    "year": 2015,
    "milestone": "Dan Spengeman: Comedian of the Year",
    "sentiment_polarity": 0.0,
    "sentiment_subjectivity": 0.0,
    "category": "music_awards",
    "vader_compound": 0.382,
    "vader_pos": 0.342,
    "vader_neg": 0.0,
    "sentiment_adjusted": 0.382,
    "topic": "Topic 2: year, comedian, anniversary, ecd",
    "life_stage": "The Road Back"
  },
  {
    "year": 2015,
    "milestone": "Janet Jackson first Artist of the Year win",
    "sentiment_polarity": 0.525,
    "sentiment_subjectivity": 0.367,
    "category": "music_awards",
    "vader_compound": 0.586,
    "vader_pos": 0.352,
    "vader_neg": 0.0,
    "sentiment_adjusted": 0.586,
    "topic": "Topic 2: year, comedian, anniversary, ecd",
    "life_stage": "The Road Back"
  },
  {
    "year": 2015,
    "milestone": "Kia Soul hits 20,000 miles (Dec 15)",
    "sentiment_polarity": 0.0,
    "sentiment_subjectivity": 0.0,
    "category": "travel",
    "vader_compound": -0.637,
    "vader_pos": 0.0,
    "vader_neg": 0.412,
    "sentiment_adjusted": 0.1,
    "topic": "Topic 5: dec, 15, 18, 12",
    "life_stage": "The Road Back"
  },
  {
    "year": 2015,
    "milestone": "USVI & Bahamas cruise (rated 10/10)",
    "sentiment_polarity": 0.0,
    "sentiment_subjectivity": 0.0,
    "category": "travel",
    "vader_compound": 0.0,
    "vader_pos": 0.0,
    "vader_neg": 0.0,
    "sentiment_adjusted": 0.05,
    "topic": "Topic 4: cruise, croatia, years, 10",
    "life_stage": "The Road Back"
  },
  {
    "year": 2016,
    "milestone": "Cornhole: 254-98, 38 cornholios",
    "sentiment_polarity": 0.0,
    "sentiment_subjectivity": 0.0,
    "category": "sports",
    "vader_compound": 0.0,
    "vader_pos": 0.0,
    "vader_neg": 0.0,
    "sentiment_adjusted": 0.0,
    "topic": "Topic 4: cruise, croatia, years, 10",
    "life_stage": "The Road Back"
  },
  {
    "year": 2016,
    "milestone": "Lauren Winston: Comedian of the Year",
    "sentiment_polarity": 0.0,
    "sentiment_subjectivity": 0.0,
    "category": "music_awards",
    "vader_compound": 0.382,
    "vader_pos": 0.342,
    "vader_neg": 0.0,
    "sentiment_adjusted": 0.382,
    "topic": "Topic 2: year, comedian, anniversary, ecd",
    "life_stage": "The Road Back"
  },
  {
    "year": 2016,
    "milestone": "Manager of the Year award",
    "sentiment_polarity": 0.0,
    "sentiment_subjectivity": 0.0,
    "category": "career",
    "vader_compound": 0.542,
    "vader_pos": 0.467,
    "vader_neg": 0.0,
    "sentiment_adjusted": 0.542,
    "topic": "Topic 2: year, comedian, anniversary, ecd",
    "life_stage": "The Road Back"
  },
  {
    "year": 2016,
    "milestone": "Spengeman-Mullins wedding",
    "sentiment_polarity": 0.0,
    "sentiment_subjectivity": 0.0,
    "category": "social",
    "vader_compound": 0.0,
    "vader_pos": 0.0,
    "vader_neg": 0.0,
    "sentiment_adjusted": 0.0,
    "topic": "Topic 3: trip, ski, 000, road",
    "life_stage": "The Road Back"
  },
  {
    "year": 2016,
    "milestone": "St. Lucia/Dominica/Antigua cruise",
    "sentiment_polarity": 0.0,
    "sentiment_subjectivity": 0.0,
    "category": "travel",
    "vader_compound": 0.0,
    "vader_pos": 0.0,
    "vader_neg": 0.0,
    "sentiment_adjusted": 0.05,
    "topic": "Topic 4: cruise, croatia, years, 10",
    "life_stage": "The Road Back"
  },
  {
    "year": 2016,
    "milestone": "Table tennis: 62-4 (93.9%)",
    "sentiment_polarity": 0.0,
    "sentiment_subjectivity": 0.0,
    "category": "sports",
    "vader_compound": 0.0,
    "vader_pos": 0.0,
    "vader_neg": 0.0,
    "sentiment_adjusted": 0.0,
    "topic": "Topic 5: dec, 15, 18, 12",
    "life_stage": "The Road Back"
  },
  {
    "year": 2016,
    "milestone": "WrestleMania 32 (100,000+) \u2014 'greatest WWE experience of all-time'",
    "sentiment_polarity": 1.0,
    "sentiment_subjectivity": 1.0,
    "category": "wwe",
    "vader_compound": 0.637,
    "vader_pos": 0.375,
    "vader_neg": 0.0,
    "sentiment_adjusted": 0.687,
    "topic": "Topic 6: wwe, event, oct, mar",
    "life_stage": "The Road Back"
  },
  {
    "year": 2017,
    "milestone": "14 staples removed (Dec 26)",
    "sentiment_polarity": 0.0,
    "sentiment_subjectivity": 0.0,
    "category": "personal",
    "vader_compound": 0.0,
    "vader_pos": 0.0,
    "vader_neg": 0.0,
    "sentiment_adjusted": 0.0,
    "topic": "Topic 5: dec, 15, 18, 12",
    "life_stage": "The Road Back"
  },
  {
    "year": 2017,
    "milestone": "Alaska cruise + Seattle (Mendenhall Glacier)",
    "sentiment_polarity": 0.0,
    "sentiment_subjectivity": 0.0,
    "category": "travel",
    "vader_compound": 0.0,
    "vader_pos": 0.0,
    "vader_neg": 0.0,
    "sentiment_adjusted": 0.05,
    "topic": "Topic 4: cruise, croatia, years, 10",
    "life_stage": "The Road Back"
  },
  {
    "year": 2017,
    "milestone": "Broken left pinky \u2014 volleyball career paused (Mar 26)",
    "sentiment_polarity": -0.2,
    "sentiment_subjectivity": 0.2,
    "category": "career",
    "vader_compound": -0.477,
    "vader_pos": 0.0,
    "vader_neg": 0.307,
    "sentiment_adjusted": -0.477,
    "topic": "Topic 7: aug, 16, dodgeball, 21",
    "life_stage": "The Road Back"
  },
  {
    "year": 2017,
    "milestone": "California trip 600+ miles for Matt & Gina wedding",
    "sentiment_polarity": 0.0,
    "sentiment_subjectivity": 0.0,
    "category": "travel",
    "vader_compound": 0.0,
    "vader_pos": 0.0,
    "vader_neg": 0.0,
    "sentiment_adjusted": 0.05,
    "topic": "Topic 3: trip, ski, 000, road",
    "life_stage": "The Road Back"
  },
  {
    "year": 2017,
    "milestone": "Cornhole: 27-2 record on cruise",
    "sentiment_polarity": 0.0,
    "sentiment_subjectivity": 0.0,
    "category": "travel",
    "vader_compound": 0.2,
    "vader_pos": 0.0,
    "vader_neg": 0.0,
    "sentiment_adjusted": 0.3,
    "topic": "Topic 4: cruise, croatia, years, 10",
    "life_stage": "The Road Back"
  },
  {
    "year": 2017,
    "milestone": "ECD 12-Year Anniversary (Sep 2)",
    "sentiment_polarity": 0.0,
    "sentiment_subjectivity": 0.0,
    "category": "ecd",
    "vader_compound": 0.0,
    "vader_pos": 0.0,
    "vader_neg": 0.0,
    "sentiment_adjusted": 0.0,
    "topic": "Topic 2: year, comedian, anniversary, ecd",
    "life_stage": "The Road Back"
  },
  {
    "year": 2017,
    "milestone": "Escape Room completed in 45:43 (Jan 15)",
    "sentiment_polarity": 0.0,
    "sentiment_subjectivity": 0.0,
    "category": "entertainment",
    "vader_compound": 0.178,
    "vader_pos": 0.221,
    "vader_neg": 0.0,
    "sentiment_adjusted": 0.178,
    "topic": "Topic 5: dec, 15, 18, 12",
    "life_stage": "The Road Back"
  },
  {
    "year": 2017,
    "milestone": "Father's 60th birthday (Jul 29)",
    "sentiment_polarity": 0.0,
    "sentiment_subjectivity": 0.0,
    "category": "social",
    "vader_compound": 0.0,
    "vader_pos": 0.0,
    "vader_neg": 0.0,
    "sentiment_adjusted": 0.0,
    "topic": "Topic 8: jul, 29, birthday, married",
    "life_stage": "The Road Back"
  },
  {
    "year": 2017,
    "milestone": "Kevin & Leah engaged",
    "sentiment_polarity": 0.0,
    "sentiment_subjectivity": 0.0,
    "category": "other",
    "vader_compound": 0.402,
    "vader_pos": 0.574,
    "vader_neg": 0.0,
    "sentiment_adjusted": 0.502,
    "topic": "Topic 8: jul, 29, birthday, married",
    "life_stage": "The Road Back"
  },
  {
    "year": 2017,
    "milestone": "L5-S1 herniation \u2192 microdiscectomy surgery (Dec 15) at Riverview hospital",
    "sentiment_polarity": 0.0,
    "sentiment_subjectivity": 0.0,
    "category": "health",
    "vader_compound": -0.2,
    "vader_pos": 0.0,
    "vader_neg": 0.0,
    "sentiment_adjusted": -0.3,
    "topic": "Topic 5: dec, 15, 18, 12",
    "life_stage": "The Road Back"
  },
  {
    "year": 2017,
    "milestone": "Silver League Champions volleyball (Aug 30)",
    "sentiment_polarity": 0.0,
    "sentiment_subjectivity": 0.0,
    "category": "sports",
    "vader_compound": 0.527,
    "vader_pos": 0.405,
    "vader_neg": 0.0,
    "sentiment_adjusted": 0.527,
    "topic": "Topic 7: aug, 16, dodgeball, 21",
    "life_stage": "The Road Back"
  },
  {
    "year": 2017,
    "milestone": "SummerSlam 20-year personal story complete (Aug 20)",
    "sentiment_polarity": 0.05,
    "sentiment_subjectivity": 0.35,
    "category": "wwe",
    "vader_compound": 0.0,
    "vader_pos": 0.0,
    "vader_neg": 0.0,
    "sentiment_adjusted": 0.05,
    "topic": "Topic 7: aug, 16, dodgeball, 21",
    "life_stage": "The Road Back"
  },
  {
    "year": 2017,
    "milestone": "WrestleMania 33 (Apr 2)",
    "sentiment_polarity": 0.0,
    "sentiment_subjectivity": 0.0,
    "category": "wwe",
    "vader_compound": 0.0,
    "vader_pos": 0.0,
    "vader_neg": 0.0,
    "sentiment_adjusted": 0.05,
    "topic": "Topic 7: aug, 16, dodgeball, 21",
    "life_stage": "The Road Back"
  },
  {
    "year": 2018,
    "milestone": "34th birthday (Sep 27)",
    "sentiment_polarity": 0.0,
    "sentiment_subjectivity": 0.0,
    "category": "social",
    "vader_compound": 0.0,
    "vader_pos": 0.0,
    "vader_neg": 0.0,
    "sentiment_adjusted": 0.0,
    "topic": "Topic 1: sep, 27, turned, birthday",
    "life_stage": "Resurrection"
  },
  {
    "year": 2018,
    "milestone": "6th cruise in 6 years",
    "sentiment_polarity": 0.0,
    "sentiment_subjectivity": 0.0,
    "category": "travel",
    "vader_compound": 0.0,
    "vader_pos": 0.0,
    "vader_neg": 0.0,
    "sentiment_adjusted": 0.05,
    "topic": "Topic 4: cruise, croatia, years, 10",
    "life_stage": "Resurrection"
  },
  {
    "year": 2018,
    "milestone": "Arthur Knott (Artie) passed away (Feb 2)",
    "sentiment_polarity": 0.0,
    "sentiment_subjectivity": 0.0,
    "category": "other",
    "vader_compound": 0.0,
    "vader_pos": 0.0,
    "vader_neg": 0.0,
    "sentiment_adjusted": 0.0,
    "topic": "Topic 8: jul, 29, birthday, married",
    "life_stage": "Resurrection"
  },
  {
    "year": 2018,
    "milestone": "Became a pickleball believer (Aug 16)",
    "sentiment_polarity": 0.0,
    "sentiment_subjectivity": 0.0,
    "category": "sports",
    "vader_compound": 0.0,
    "vader_pos": 0.0,
    "vader_neg": 0.0,
    "sentiment_adjusted": 0.0,
    "topic": "Topic 7: aug, 16, dodgeball, 21",
    "life_stage": "Resurrection"
  },
  {
    "year": 2018,
    "milestone": "Best tennis comeback: won from 0-6 deficit (Dec 23)",
    "sentiment_polarity": 1.0,
    "sentiment_subjectivity": 0.3,
    "category": "sports",
    "vader_compound": 0.735,
    "vader_pos": 0.476,
    "vader_neg": 0.163,
    "sentiment_adjusted": 0.835,
    "topic": "Topic 5: dec, 15, 18, 12",
    "life_stage": "Resurrection"
  },
  {
    "year": 2018,
    "milestone": "Brother Michael married Maggie (Jun 29)",
    "sentiment_polarity": 0.25,
    "sentiment_subjectivity": 0.25,
    "category": "family",
    "vader_compound": 0.0,
    "vader_pos": 0.0,
    "vader_neg": 0.0,
    "sentiment_adjusted": 0.0,
    "topic": "Topic 8: jul, 29, birthday, married",
    "life_stage": "Resurrection"
  },
  {
    "year": 2018,
    "milestone": "Engagement ring purchased in Croatia",
    "sentiment_polarity": 0.0,
    "sentiment_subjectivity": 0.0,
    "category": "relationship",
    "vader_compound": 0.459,
    "vader_pos": 0.429,
    "vader_neg": 0.0,
    "sentiment_adjusted": 0.459,
    "topic": "Topic 4: cruise, croatia, years, 10",
    "life_stage": "Resurrection"
  },
  {
    "year": 2018,
    "milestone": "Fever 100.3 on NYE",
    "sentiment_polarity": 0.0,
    "sentiment_subjectivity": 0.0,
    "category": "health",
    "vader_compound": 0.0,
    "vader_pos": 0.0,
    "vader_neg": 0.0,
    "sentiment_adjusted": -0.1,
    "topic": "Topic 7: aug, 16, dodgeball, 21",
    "life_stage": "Resurrection"
  },
  {
    "year": 2018,
    "milestone": "Mediterranean cruise (Slovenia, Italy, Greece, Malta, Croatia \u2014 5 countries, 2 weeks)",
    "sentiment_polarity": 0.0,
    "sentiment_subjectivity": 0.0,
    "category": "travel",
    "vader_compound": 0.0,
    "vader_pos": 0.0,
    "vader_neg": 0.0,
    "sentiment_adjusted": 0.05,
    "topic": "Topic 4: cruise, croatia, years, 10",
    "life_stage": "Resurrection"
  },
  {
    "year": 2018,
    "milestone": "New Hampshire trip (Sep 19-22)",
    "sentiment_polarity": 0.136,
    "sentiment_subjectivity": 0.455,
    "category": "travel",
    "vader_compound": 0.0,
    "vader_pos": 0.0,
    "vader_neg": 0.0,
    "sentiment_adjusted": 0.05,
    "topic": "Topic 3: trip, ski, 000, road",
    "life_stage": "Resurrection"
  },
  {
    "year": 2018,
    "milestone": "Reminiscence Coordinator role at Sunrise of Wall (started Oct 22)",
    "sentiment_polarity": 0.0,
    "sentiment_subjectivity": 0.0,
    "category": "career",
    "vader_compound": 0.0,
    "vader_pos": 0.0,
    "vader_neg": 0.0,
    "sentiment_adjusted": 0.0,
    "topic": "Topic 6: wwe, event, oct, mar",
    "life_stage": "Resurrection"
  },
  {
    "year": 2018,
    "milestone": "Sisters turned 16 \u2014 Six Flags Great Adventure (Aug 27)",
    "sentiment_polarity": 0.8,
    "sentiment_subjectivity": 0.75,
    "category": "family",
    "vader_compound": 0.751,
    "vader_pos": 0.478,
    "vader_neg": 0.0,
    "sentiment_adjusted": 0.751,
    "topic": "Topic 7: aug, 16, dodgeball, 21",
    "life_stage": "Resurrection"
  },
  {
    "year": 2018,
    "milestone": "Won Weezer tickets as 94.3 radio 9th caller (Nov 26)",
    "sentiment_polarity": 0.0,
    "sentiment_subjectivity": 0.0,
    "category": "entertainment",
    "vader_compound": 0.572,
    "vader_pos": 0.291,
    "vader_neg": 0.0,
    "sentiment_adjusted": 0.672,
    "topic": "Topic 5: dec, 15, 18, 12",
    "life_stage": "Resurrection"
  },
  {
    "year": 2019,
    "milestone": "'2020, challenge accepted' (Dec 31)",
    "sentiment_polarity": 0.0,
    "sentiment_subjectivity": 0.0,
    "category": "other",
    "vader_compound": 0.34,
    "vader_pos": 0.531,
    "vader_neg": 0.0,
    "sentiment_adjusted": 0.34,
    "topic": "Topic 5: dec, 15, 18, 12",
    "life_stage": "Resurrection"
  },
  {
    "year": 2019,
    "milestone": "1,000th CHA game vs Pops Tronolone (May 22)",
    "sentiment_polarity": -0.4,
    "sentiment_subjectivity": 0.4,
    "category": "family",
    "vader_compound": 0.0,
    "vader_pos": 0.0,
    "vader_neg": 0.0,
    "sentiment_adjusted": 0.0,
    "topic": "Topic 7: aug, 16, dodgeball, 21",
    "life_stage": "Resurrection"
  },
  {
    "year": 2019,
    "milestone": "35th birthday \u2014 'Halfway to 70' (Sep 25-27)",
    "sentiment_polarity": 0.0,
    "sentiment_subjectivity": 0.0,
    "category": "social",
    "vader_compound": 0.0,
    "vader_pos": 0.0,
    "vader_neg": 0.0,
    "sentiment_adjusted": 0.0,
    "topic": "Topic 1: sep, 27, turned, birthday",
    "life_stage": "Resurrection"
  },
  {
    "year": 2019,
    "milestone": "7th Major ECD championship (Aug 17)",
    "sentiment_polarity": 0.062,
    "sentiment_subjectivity": 0.5,
    "category": "ecd",
    "vader_compound": 0.44,
    "vader_pos": 0.367,
    "vader_neg": 0.0,
    "sentiment_adjusted": 0.54,
    "topic": "Topic 7: aug, 16, dodgeball, 21",
    "life_stage": "Resurrection"
  },
  {
    "year": 2019,
    "milestone": "Australia & New Zealand \u2014 'the best, the longest, and the greatest' (19 days, Jan 12-31)",
    "sentiment_polarity": 0.712,
    "sentiment_subjectivity": 0.585,
    "category": "travel",
    "vader_compound": 0.856,
    "vader_pos": 0.412,
    "vader_neg": 0.0,
    "sentiment_adjusted": 0.905,
    "topic": "Topic 5: dec, 15, 18, 12",
    "life_stage": "Resurrection"
  },
  {
    "year": 2019,
    "milestone": "Became Uncle John",
    "sentiment_polarity": 0.0,
    "sentiment_subjectivity": 0.0,
    "category": "other",
    "vader_compound": 0.0,
    "vader_pos": 0.0,
    "vader_neg": 0.0,
    "sentiment_adjusted": 0.0,
    "topic": "Topic 7: aug, 16, dodgeball, 21",
    "life_stage": "Resurrection"
  },
  {
    "year": 2019,
    "milestone": "DC Pride Weekend (Jun 22-24)",
    "sentiment_polarity": 0.0,
    "sentiment_subjectivity": 0.0,
    "category": "other",
    "vader_compound": 0.34,
    "vader_pos": 0.375,
    "vader_neg": 0.0,
    "sentiment_adjusted": 0.34,
    "topic": "Topic 8: jul, 29, birthday, married",
    "life_stage": "Resurrection"
  },
  {
    "year": 2019,
    "milestone": "Inaugural 'Steal Bingo' (Nov 23)",
    "sentiment_polarity": 0.0,
    "sentiment_subjectivity": 0.0,
    "category": "other",
    "vader_compound": -0.494,
    "vader_pos": 0.0,
    "vader_neg": 0.444,
    "sentiment_adjusted": -0.494,
    "topic": "Topic 5: dec, 15, 18, 12",
    "life_stage": "Resurrection"
  },
  {
    "year": 2019,
    "milestone": "Nephew Julian John Tronolone born (Aug 23)",
    "sentiment_polarity": 0.0,
    "sentiment_subjectivity": 0.0,
    "category": "family",
    "vader_compound": 0.0,
    "vader_pos": 0.0,
    "vader_neg": 0.0,
    "sentiment_adjusted": 0.0,
    "topic": "Topic 7: aug, 16, dodgeball, 21",
    "life_stage": "Resurrection"
  },
  {
    "year": 2019,
    "milestone": "RK's 30th birthday in Atlantic City (Dec 15-16)",
    "sentiment_polarity": 0.0,
    "sentiment_subjectivity": 0.0,
    "category": "relationship",
    "vader_compound": 0.0,
    "vader_pos": 0.0,
    "vader_neg": 0.0,
    "sentiment_adjusted": 0.0,
    "topic": "Topic 5: dec, 15, 18, 12",
    "life_stage": "Resurrection"
  },
  {
    "year": 2019,
    "milestone": "Strep throat + kidney stone removal",
    "sentiment_polarity": 0.0,
    "sentiment_subjectivity": 0.0,
    "category": "health",
    "vader_compound": 0.0,
    "vader_pos": 0.0,
    "vader_neg": 0.0,
    "sentiment_adjusted": -0.1,
    "topic": "Topic 5: dec, 15, 18, 12",
    "life_stage": "Resurrection"
  },
  {
    "year": 2019,
    "milestone": "U.S. Open: Nadal vs Medvedev final, 3rd longest in 100+ years (Sep 8)",
    "sentiment_polarity": 0.125,
    "sentiment_subjectivity": 0.625,
    "category": "entertainment",
    "vader_compound": 0.44,
    "vader_pos": 0.195,
    "vader_neg": 0.0,
    "sentiment_adjusted": 0.44,
    "topic": "Topic 1: sep, 27, turned, birthday",
    "life_stage": "Resurrection"
  },
  {
    "year": 2019,
    "milestone": "Weezer concert at sold-out MSG (Mar 12)",
    "sentiment_polarity": 0.0,
    "sentiment_subjectivity": 0.0,
    "category": "entertainment",
    "vader_compound": 0.0,
    "vader_pos": 0.0,
    "vader_neg": 0.0,
    "sentiment_adjusted": 0.0,
    "topic": "Topic 7: aug, 16, dodgeball, 21",
    "life_stage": "Resurrection"
  },
  {
    "year": 2019,
    "milestone": "Wisconsin Trip 1: Moore-Tronolone wedding (May 31-Jun 2)",
    "sentiment_polarity": 0.0,
    "sentiment_subjectivity": 0.0,
    "category": "travel",
    "vader_compound": 0.0,
    "vader_pos": 0.0,
    "vader_neg": 0.0,
    "sentiment_adjusted": 0.05,
    "topic": "Topic 3: trip, ski, 000, road",
    "life_stage": "Resurrection"
  },
  {
    "year": 2019,
    "milestone": "Wisconsin Trip 2: Lambeau Field 78,000+ (Sep 20-23)",
    "sentiment_polarity": 0.0,
    "sentiment_subjectivity": 0.0,
    "category": "travel",
    "vader_compound": 0.0,
    "vader_pos": 0.0,
    "vader_neg": 0.0,
    "sentiment_adjusted": 0.05,
    "topic": "Topic 3: trip, ski, 000, road",
    "life_stage": "Resurrection"
  },
  {
    "year": 2020,
    "milestone": "4th skydive (Oct 3, mother witnessed) \u2014 'easiest of the freefalls'",
    "sentiment_polarity": 0.0,
    "sentiment_subjectivity": 0.0,
    "category": "sports",
    "vader_compound": 0.421,
    "vader_pos": 0.237,
    "vader_neg": 0.0,
    "sentiment_adjusted": 0.421,
    "topic": "Topic 6: wwe, event, oct, mar",
    "life_stage": "Resurrection"
  },
  {
    "year": 2020,
    "milestone": "90th WWE event (Mar 8, 17th with RL)",
    "sentiment_polarity": 0.0,
    "sentiment_subjectivity": 0.0,
    "category": "wwe",
    "vader_compound": 0.0,
    "vader_pos": 0.0,
    "vader_neg": 0.0,
    "sentiment_adjusted": 0.05,
    "topic": "Topic 6: wwe, event, oct, mar",
    "life_stage": "Resurrection"
  },
  {
    "year": 2020,
    "milestone": "Asian expedition: Singapore, Thailand, Cambodia, Vietnam, Hong Kong (17 days Jan-Feb)",
    "sentiment_polarity": 0.0,
    "sentiment_subjectivity": 0.0,
    "category": "travel",
    "vader_compound": 0.0,
    "vader_pos": 0.0,
    "vader_neg": 0.0,
    "sentiment_adjusted": 0.05,
    "topic": "Topic 5: dec, 15, 18, 12",
    "life_stage": "Resurrection"
  },
  {
    "year": 2020,
    "milestone": "Assisted Living Manager at Sunrise of Jackson (started Sep 28)",
    "sentiment_polarity": 0.0,
    "sentiment_subjectivity": 0.0,
    "category": "career",
    "vader_compound": 0.0,
    "vader_pos": 0.0,
    "vader_neg": 0.0,
    "sentiment_adjusted": 0.0,
    "topic": "Topic 1: sep, 27, turned, birthday",
    "life_stage": "Resurrection"
  },
  {
    "year": 2020,
    "milestone": "ECD 15th birthday (Aug 22-23)",
    "sentiment_polarity": 0.0,
    "sentiment_subjectivity": 0.0,
    "category": "ecd",
    "vader_compound": 0.0,
    "vader_pos": 0.0,
    "vader_neg": 0.0,
    "sentiment_adjusted": 0.0,
    "topic": "Topic 7: aug, 16, dodgeball, 21",
    "life_stage": "Resurrection"
  },
  {
    "year": 2020,
    "milestone": "Grace & Megan graduate high school",
    "sentiment_polarity": 0.16,
    "sentiment_subjectivity": 0.54,
    "category": "family",
    "vader_compound": 0.421,
    "vader_pos": 0.412,
    "vader_neg": 0.0,
    "sentiment_adjusted": 0.421,
    "topic": "Topic 4: cruise, croatia, years, 10",
    "life_stage": "Resurrection"
  },
  {
    "year": 2020,
    "milestone": "Kevin & Leah married Feb 29 (leap day)",
    "sentiment_polarity": 0.25,
    "sentiment_subjectivity": 0.25,
    "category": "other",
    "vader_compound": 0.0,
    "vader_pos": 0.0,
    "vader_neg": 0.0,
    "sentiment_adjusted": 0.0,
    "topic": "Topic 8: jul, 29, birthday, married",
    "life_stage": "Resurrection"
  },
  {
    "year": 2020,
    "milestone": "Medical quarantine (Mar 26 \u2013 Apr 16) + muscle gain comeback",
    "sentiment_polarity": 0.0,
    "sentiment_subjectivity": 0.0,
    "category": "health",
    "vader_compound": 0.527,
    "vader_pos": 0.298,
    "vader_neg": 0.0,
    "sentiment_adjusted": 0.427,
    "topic": "Topic 7: aug, 16, dodgeball, 21",
    "life_stage": "Resurrection"
  },
  {
    "year": 2020,
    "milestone": "Pasta Passion & Pistols Murder Mystery NYE (Dec 31)",
    "sentiment_polarity": 0.0,
    "sentiment_subjectivity": 0.0,
    "category": "social",
    "vader_compound": -0.402,
    "vader_pos": 0.219,
    "vader_neg": 0.343,
    "sentiment_adjusted": -0.402,
    "topic": "Topic 5: dec, 15, 18, 12",
    "life_stage": "Resurrection"
  },
  {
    "year": 2020,
    "milestone": "Tennis: 6-3, 6-1 vs Blake (Dec 12)",
    "sentiment_polarity": 0.0,
    "sentiment_subjectivity": 0.0,
    "category": "sports",
    "vader_compound": 0.0,
    "vader_pos": 0.0,
    "vader_neg": 0.0,
    "sentiment_adjusted": 0.0,
    "topic": "Topic 5: dec, 15, 18, 12",
    "life_stage": "Resurrection"
  },
  {
    "year": 2020,
    "milestone": "Turned 36 (Sep 27) \u2014 skydive + birthday combined",
    "sentiment_polarity": 0.0,
    "sentiment_subjectivity": 0.0,
    "category": "sports",
    "vader_compound": 0.0,
    "vader_pos": 0.0,
    "vader_neg": 0.0,
    "sentiment_adjusted": 0.0,
    "topic": "Topic 1: sep, 27, turned, birthday",
    "life_stage": "Resurrection"
  },
  {
    "year": 2021,
    "milestone": "10-year anniversary with Rob (Jan 15)",
    "sentiment_polarity": 0.0,
    "sentiment_subjectivity": 0.0,
    "category": "relationship",
    "vader_compound": -0.557,
    "vader_pos": 0.0,
    "vader_neg": 0.419,
    "sentiment_adjusted": 0.5,
    "topic": "Topic 2: year, comedian, anniversary, ecd",
    "life_stage": "Return with the Elixir"
  },
  {
    "year": 2021,
    "milestone": "20 years between Rangers games at MSG",
    "sentiment_polarity": 0.0,
    "sentiment_subjectivity": 0.0,
    "category": "entertainment",
    "vader_compound": 0.0,
    "vader_pos": 0.0,
    "vader_neg": 0.0,
    "sentiment_adjusted": 0.0,
    "topic": "Topic 7: aug, 16, dodgeball, 21",
    "life_stage": "Return with the Elixir"
  },
  {
    "year": 2021,
    "milestone": "218-round ping pong match",
    "sentiment_polarity": 0.0,
    "sentiment_subjectivity": 0.0,
    "category": "sports",
    "vader_compound": 0.0,
    "vader_pos": 0.0,
    "vader_neg": 0.0,
    "sentiment_adjusted": 0.0,
    "topic": "Topic 1: sep, 27, turned, birthday",
    "life_stage": "Return with the Elixir"
  },
  {
    "year": 2021,
    "milestone": "25th consecutive Survivor Series \u2014 91st WWE event",
    "sentiment_polarity": 0.0,
    "sentiment_subjectivity": 0.0,
    "category": "wwe",
    "vader_compound": 0.361,
    "vader_pos": 0.294,
    "vader_neg": 0.0,
    "sentiment_adjusted": 0.411,
    "topic": "Topic 6: wwe, event, oct, mar",
    "life_stage": "Return with the Elixir"
  },
  {
    "year": 2021,
    "milestone": "37th birthday (Sep 24-28)",
    "sentiment_polarity": 0.0,
    "sentiment_subjectivity": 0.0,
    "category": "social",
    "vader_compound": 0.0,
    "vader_pos": 0.0,
    "vader_neg": 0.0,
    "sentiment_adjusted": 0.0,
    "topic": "Topic 1: sep, 27, turned, birthday",
    "life_stage": "Return with the Elixir"
  },
  {
    "year": 2021,
    "milestone": "568-day wait for Laver Cup tickets",
    "sentiment_polarity": 0.0,
    "sentiment_subjectivity": 0.0,
    "category": "entertainment",
    "vader_compound": 0.0,
    "vader_pos": 0.0,
    "vader_neg": 0.0,
    "sentiment_adjusted": 0.0,
    "topic": "Topic 1: sep, 27, turned, birthday",
    "life_stage": "Return with the Elixir"
  },
  {
    "year": 2021,
    "milestone": "8.6 lbs shrimp + 7.3 lbs crab meat consumed",
    "sentiment_polarity": 0.0,
    "sentiment_subjectivity": 0.0,
    "category": "other",
    "vader_compound": 0.0,
    "vader_pos": 0.0,
    "vader_neg": 0.0,
    "sentiment_adjusted": 0.0,
    "topic": "Topic 5: dec, 15, 18, 12",
    "life_stage": "Return with the Elixir"
  },
  {
    "year": 2021,
    "milestone": "Alexandria Virginia work assignment (Sep 20-23)",
    "sentiment_polarity": 0.0,
    "sentiment_subjectivity": 0.0,
    "category": "relationship",
    "vader_compound": 0.0,
    "vader_pos": 0.0,
    "vader_neg": 0.0,
    "sentiment_adjusted": 0.0,
    "topic": "Topic 1: sep, 27, turned, birthday",
    "life_stage": "Return with the Elixir"
  },
  {
    "year": 2021,
    "milestone": "Arizona trip: Grand Canyon, Sedona, Flagstaff",
    "sentiment_polarity": 0.5,
    "sentiment_subjectivity": 1.0,
    "category": "travel",
    "vader_compound": 0.459,
    "vader_pos": 0.375,
    "vader_neg": 0.0,
    "sentiment_adjusted": 0.509,
    "topic": "Topic 3: trip, ski, 000, road",
    "life_stage": "Return with the Elixir"
  },
  {
    "year": 2021,
    "milestone": "Danny won inaugural 'RK Quiz' (Dec 11)",
    "sentiment_polarity": 0.0,
    "sentiment_subjectivity": 0.0,
    "category": "relationship",
    "vader_compound": 0.572,
    "vader_pos": 0.381,
    "vader_neg": 0.0,
    "sentiment_adjusted": 0.672,
    "topic": "Topic 5: dec, 15, 18, 12",
    "life_stage": "Return with the Elixir"
  },
  {
    "year": 2021,
    "milestone": "Death Valley visited (Mar 16-20)",
    "sentiment_polarity": 0.0,
    "sentiment_subjectivity": 0.0,
    "category": "travel",
    "vader_compound": -0.599,
    "vader_pos": 0.0,
    "vader_neg": 0.494,
    "sentiment_adjusted": -0.549,
    "topic": "Topic 7: aug, 16, dodgeball, 21",
    "life_stage": "Return with the Elixir"
  },
  {
    "year": 2021,
    "milestone": "Ft. Lauderdale wedding attendance (May 13-18)",
    "sentiment_polarity": 0.0,
    "sentiment_subjectivity": 0.0,
    "category": "travel",
    "vader_compound": 0.0,
    "vader_pos": 0.0,
    "vader_neg": 0.0,
    "sentiment_adjusted": 0.05,
    "topic": "Topic 5: dec, 15, 18, 12",
    "life_stage": "Return with the Elixir"
  },
  {
    "year": 2021,
    "milestone": "Grand Canyon/Vegas/Utah/Colorado/Boston trip (1,000+ photos)",
    "sentiment_polarity": 0.5,
    "sentiment_subjectivity": 1.0,
    "category": "travel",
    "vader_compound": 0.459,
    "vader_pos": 0.429,
    "vader_neg": 0.0,
    "sentiment_adjusted": 0.509,
    "topic": "Topic 3: trip, ski, 000, road",
    "life_stage": "Return with the Elixir"
  },
  {
    "year": 2021,
    "milestone": "Jumped from Stratosphere in Las Vegas",
    "sentiment_polarity": 0.0,
    "sentiment_subjectivity": 0.0,
    "category": "other",
    "vader_compound": 0.0,
    "vader_pos": 0.0,
    "vader_neg": 0.0,
    "sentiment_adjusted": 0.0,
    "topic": "Topic 3: trip, ski, 000, road",
    "life_stage": "Return with the Elixir"
  },
  {
    "year": 2021,
    "milestone": "Nephew Lawrence born (Dec 23, 6:25am)",
    "sentiment_polarity": 0.0,
    "sentiment_subjectivity": 0.0,
    "category": "family",
    "vader_compound": 0.0,
    "vader_pos": 0.0,
    "vader_neg": 0.0,
    "sentiment_adjusted": 0.0,
    "topic": "Topic 5: dec, 15, 18, 12",
    "life_stage": "Return with the Elixir"
  },
  {
    "year": 2021,
    "milestone": "Sr. Resident Care Coordinator promotion (applied Jul 11, accepted Jul 23)",
    "sentiment_polarity": 0.0,
    "sentiment_subjectivity": 0.0,
    "category": "career",
    "vader_compound": 0.649,
    "vader_pos": 0.371,
    "vader_neg": 0.0,
    "sentiment_adjusted": 0.649,
    "topic": "Topic 8: jul, 29, birthday, married",
    "life_stage": "Return with the Elixir"
  },
  {
    "year": 2021,
    "milestone": "Tour de Friends events (Feb-Apr)",
    "sentiment_polarity": 0.0,
    "sentiment_subjectivity": 0.0,
    "category": "other",
    "vader_compound": 0.477,
    "vader_pos": 0.437,
    "vader_neg": 0.0,
    "sentiment_adjusted": 0.477,
    "topic": "Topic 7: aug, 16, dodgeball, 21",
    "life_stage": "Return with the Elixir"
  },
  {
    "year": 2021,
    "milestone": "Washington D.C. visit (October)",
    "sentiment_polarity": 0.0,
    "sentiment_subjectivity": 0.0,
    "category": "travel",
    "vader_compound": 0.0,
    "vader_pos": 0.0,
    "vader_neg": 0.0,
    "sentiment_adjusted": 0.05,
    "topic": "Topic 1: sep, 27, turned, birthday",
    "life_stage": "Return with the Elixir"
  },
  {
    "year": 2021,
    "milestone": "Year rated 9.8/10",
    "sentiment_polarity": 0.0,
    "sentiment_subjectivity": 0.0,
    "category": "other",
    "vader_compound": 0.0,
    "vader_pos": 0.0,
    "vader_neg": 0.0,
    "sentiment_adjusted": 0.0,
    "topic": "Topic 2: year, comedian, anniversary, ecd",
    "life_stage": "Return with the Elixir"
  },
  {
    "year": 2021,
    "milestone": "YogaSix Class 101 standing splits (Dec 12)",
    "sentiment_polarity": 0.0,
    "sentiment_subjectivity": 0.0,
    "category": "other",
    "vader_compound": 0.0,
    "vader_pos": 0.0,
    "vader_neg": 0.0,
    "sentiment_adjusted": 0.0,
    "topic": "Topic 5: dec, 15, 18, 12",
    "life_stage": "Return with the Elixir"
  },
  {
    "year": 2022,
    "milestone": "#100 Award",
    "sentiment_polarity": 0.0,
    "sentiment_subjectivity": 0.0,
    "category": "other",
    "vader_compound": 0.542,
    "vader_pos": 0.778,
    "vader_neg": 0.0,
    "sentiment_adjusted": 0.542,
    "topic": "Topic 7: aug, 16, dodgeball, 21",
    "life_stage": "Return with the Elixir"
  },
  {
    "year": 2022,
    "milestone": "California/Oregon vacation (Golden Gate, Redwoods, Portland)",
    "sentiment_polarity": 0.3,
    "sentiment_subjectivity": 0.5,
    "category": "other",
    "vader_compound": 0.0,
    "vader_pos": 0.0,
    "vader_neg": 0.0,
    "sentiment_adjusted": 0.0,
    "topic": "Topic 3: trip, ski, 000, road",
    "life_stage": "Return with the Elixir"
  },
  {
    "year": 2022,
    "milestone": "Connecticut work assignment (Sunrise Wilton)",
    "sentiment_polarity": 0.0,
    "sentiment_subjectivity": 0.0,
    "category": "career",
    "vader_compound": 0.0,
    "vader_pos": 0.0,
    "vader_neg": 0.0,
    "sentiment_adjusted": 0.0,
    "topic": "Topic 1: sep, 27, turned, birthday",
    "life_stage": "Return with the Elixir"
  },
  {
    "year": 2022,
    "milestone": "ECD FallFest",
    "sentiment_polarity": 0.0,
    "sentiment_subjectivity": 0.0,
    "category": "ecd",
    "vader_compound": 0.0,
    "vader_pos": 0.0,
    "vader_neg": 0.0,
    "sentiment_adjusted": 0.0,
    "topic": "Topic 2: year, comedian, anniversary, ecd",
    "life_stage": "Return with the Elixir"
  },
  {
    "year": 2022,
    "milestone": "Five Boro Bike Tour (40 miles)",
    "sentiment_polarity": 0.0,
    "sentiment_subjectivity": 0.0,
    "category": "travel",
    "vader_compound": 0.0,
    "vader_pos": 0.0,
    "vader_neg": 0.0,
    "sentiment_adjusted": 0.05,
    "topic": "Topic 3: trip, ski, 000, road",
    "life_stage": "Return with the Elixir"
  },
  {
    "year": 2022,
    "milestone": "Gram's 90th birthday",
    "sentiment_polarity": 0.0,
    "sentiment_subjectivity": 0.0,
    "category": "social",
    "vader_compound": 0.0,
    "vader_pos": 0.0,
    "vader_neg": 0.0,
    "sentiment_adjusted": 0.0,
    "topic": "Topic 8: jul, 29, birthday, married",
    "life_stage": "Return with the Elixir"
  },
  {
    "year": 2022,
    "milestone": "Hunter Mountain NY ski trip (winter)",
    "sentiment_polarity": 0.0,
    "sentiment_subjectivity": 0.0,
    "category": "other",
    "vader_compound": 0.0,
    "vader_pos": 0.0,
    "vader_neg": 0.0,
    "sentiment_adjusted": 0.0,
    "topic": "Topic 3: trip, ski, 000, road",
    "life_stage": "Return with the Elixir"
  },
  {
    "year": 2022,
    "milestone": "Knicks game (100-97 victory)",
    "sentiment_polarity": -0.4,
    "sentiment_subjectivity": 0.4,
    "category": "entertainment",
    "vader_compound": 0.0,
    "vader_pos": 0.0,
    "vader_neg": 0.0,
    "sentiment_adjusted": 0.0,
    "topic": "Topic 7: aug, 16, dodgeball, 21",
    "life_stage": "Return with the Elixir"
  },
  {
    "year": 2022,
    "milestone": "Megan's Brookdale graduation",
    "sentiment_polarity": 0.0,
    "sentiment_subjectivity": 0.0,
    "category": "family",
    "vader_compound": 0.0,
    "vader_pos": 0.0,
    "vader_neg": 0.0,
    "sentiment_adjusted": 0.0,
    "topic": "Topic 4: cruise, croatia, years, 10",
    "life_stage": "Return with the Elixir"
  },
  {
    "year": 2022,
    "milestone": "North Carolina/Tennessee road trip (March)",
    "sentiment_polarity": 0.0,
    "sentiment_subjectivity": 0.0,
    "category": "other",
    "vader_compound": 0.0,
    "vader_pos": 0.0,
    "vader_neg": 0.0,
    "sentiment_adjusted": 0.0,
    "topic": "Topic 3: trip, ski, 000, road",
    "life_stage": "Return with the Elixir"
  },
  {
    "year": 2022,
    "milestone": "PSU White Out football weekend",
    "sentiment_polarity": 0.0,
    "sentiment_subjectivity": 0.0,
    "category": "other",
    "vader_compound": 0.0,
    "vader_pos": 0.0,
    "vader_neg": 0.0,
    "sentiment_adjusted": 0.0,
    "topic": "Topic 7: aug, 16, dodgeball, 21",
    "life_stage": "Return with the Elixir"
  },
  {
    "year": 2022,
    "milestone": "Rangers playoff run (triple-OT game at MSG)",
    "sentiment_polarity": -0.4,
    "sentiment_subjectivity": 0.4,
    "category": "travel",
    "vader_compound": 0.0,
    "vader_pos": 0.0,
    "vader_neg": 0.0,
    "sentiment_adjusted": 0.05,
    "topic": "Topic 7: aug, 16, dodgeball, 21",
    "life_stage": "Return with the Elixir"
  },
  {
    "year": 2022,
    "milestone": "Undertaker inducted into Hall of Fame",
    "sentiment_polarity": 0.0,
    "sentiment_subjectivity": 0.0,
    "category": "wwe",
    "vader_compound": 0.44,
    "vader_pos": 0.367,
    "vader_neg": 0.0,
    "sentiment_adjusted": 0.49,
    "topic": "Topic 5: dec, 15, 18, 12",
    "life_stage": "Return with the Elixir"
  },
  {
    "year": 2022,
    "milestone": "Yankees game attended",
    "sentiment_polarity": -0.4,
    "sentiment_subjectivity": 0.4,
    "category": "other",
    "vader_compound": 0.0,
    "vader_pos": 0.0,
    "vader_neg": 0.0,
    "sentiment_adjusted": 0.0,
    "topic": "Topic 2: year, comedian, anniversary, ecd",
    "life_stage": "Return with the Elixir"
  },
  {
    "year": 2023,
    "milestone": "15-year anniversary of 'personal liberation day'",
    "sentiment_polarity": 0.0,
    "sentiment_subjectivity": 0.3,
    "category": "relationship",
    "vader_compound": 0.0,
    "vader_pos": 0.0,
    "vader_neg": 0.0,
    "sentiment_adjusted": 0.0,
    "topic": "Topic 2: year, comedian, anniversary, ecd",
    "life_stage": "Return with the Elixir"
  },
  {
    "year": 2023,
    "milestone": "Broadway: Hadestown, Aladdin, Chicago (3 shows in one year)",
    "sentiment_polarity": 0.0,
    "sentiment_subjectivity": 0.0,
    "category": "entertainment",
    "vader_compound": 0.0,
    "vader_pos": 0.0,
    "vader_neg": 0.0,
    "sentiment_adjusted": 0.0,
    "topic": "Topic 2: year, comedian, anniversary, ecd",
    "life_stage": "Return with the Elixir"
  },
  {
    "year": 2023,
    "milestone": "Closed on house at Mill Creek Court (Dec 18)",
    "sentiment_polarity": -0.1,
    "sentiment_subjectivity": 0.1,
    "category": "personal",
    "vader_compound": 0.0,
    "vader_pos": 0.0,
    "vader_neg": 0.0,
    "sentiment_adjusted": 0.0,
    "topic": "Topic 5: dec, 15, 18, 12",
    "life_stage": "Return with the Elixir"
  },
  {
    "year": 2023,
    "milestone": "Executive Director role began at Media, PA location (July)",
    "sentiment_polarity": 0.0,
    "sentiment_subjectivity": 0.0,
    "category": "other",
    "vader_compound": 0.0,
    "vader_pos": 0.0,
    "vader_neg": 0.0,
    "sentiment_adjusted": 0.0,
    "topic": "Topic 8: jul, 29, birthday, married",
    "life_stage": "Return with the Elixir"
  },
  {
    "year": 2023,
    "milestone": "Six Flags Great Adventure visits (multiple)",
    "sentiment_polarity": 0.4,
    "sentiment_subjectivity": 0.375,
    "category": "other",
    "vader_compound": 0.751,
    "vader_pos": 0.615,
    "vader_neg": 0.0,
    "sentiment_adjusted": 0.751,
    "topic": "Topic 7: aug, 16, dodgeball, 21",
    "life_stage": "Return with the Elixir"
  },
  {
    "year": 2023,
    "milestone": "Super Bowl LVII in Phoenix \u2014 'most spectacular day I've ever experienced'",
    "sentiment_polarity": 0.558,
    "sentiment_subjectivity": 0.742,
    "category": "entertainment",
    "vader_compound": 0.599,
    "vader_pos": 0.281,
    "vader_neg": 0.0,
    "sentiment_adjusted": 0.599,
    "topic": "Topic 2: year, comedian, anniversary, ecd",
    "life_stage": "Return with the Elixir"
  },
  {
    "year": 2024,
    "milestone": "30 blue crabs caught (personal best)",
    "sentiment_polarity": 0.333,
    "sentiment_subjectivity": 0.233,
    "category": "other",
    "vader_compound": 0.0,
    "vader_pos": 0.0,
    "vader_neg": 0.0,
    "sentiment_adjusted": 0.0,
    "topic": "Topic 7: aug, 16, dodgeball, 21",
    "life_stage": "Return with the Elixir"
  },
  {
    "year": 2024,
    "milestone": "Bowling 180+ average",
    "sentiment_polarity": -0.15,
    "sentiment_subjectivity": 0.4,
    "category": "sports",
    "vader_compound": 0.0,
    "vader_pos": 0.0,
    "vader_neg": 0.0,
    "sentiment_adjusted": 0.0,
    "topic": "Topic 1: sep, 27, turned, birthday",
    "life_stage": "Return with the Elixir"
  },
  {
    "year": 2024,
    "milestone": "Fenwick Island/Delaware trip",
    "sentiment_polarity": 0.0,
    "sentiment_subjectivity": 0.0,
    "category": "travel",
    "vader_compound": 0.0,
    "vader_pos": 0.0,
    "vader_neg": 0.0,
    "sentiment_adjusted": 0.05,
    "topic": "Topic 3: trip, ski, 000, road",
    "life_stage": "Return with the Elixir"
  },
  {
    "year": 2024,
    "milestone": "Grandmother passed (Oct 21, 11:57 PM, age 92)",
    "sentiment_polarity": 0.0,
    "sentiment_subjectivity": 0.0,
    "category": "family",
    "vader_compound": 0.0,
    "vader_pos": 0.0,
    "vader_neg": 0.0,
    "sentiment_adjusted": 0.0,
    "topic": "Topic 6: wwe, event, oct, mar",
    "life_stage": "Return with the Elixir"
  },
  {
    "year": 2024,
    "milestone": "Julian's 5th birthday (Aug 25)",
    "sentiment_polarity": 0.0,
    "sentiment_subjectivity": 0.0,
    "category": "family",
    "vader_compound": 0.0,
    "vader_pos": 0.0,
    "vader_neg": 0.0,
    "sentiment_adjusted": 0.0,
    "topic": "Topic 7: aug, 16, dodgeball, 21",
    "life_stage": "Return with the Elixir"
  },
  {
    "year": 2024,
    "milestone": "Kidney stones (Dec 18 & 20 hospitalizations)",
    "sentiment_polarity": 0.0,
    "sentiment_subjectivity": 0.0,
    "category": "health",
    "vader_compound": 0.0,
    "vader_pos": 0.0,
    "vader_neg": 0.0,
    "sentiment_adjusted": -0.1,
    "topic": "Topic 5: dec, 15, 18, 12",
    "life_stage": "Return with the Elixir"
  },
  {
    "year": 2024,
    "milestone": "Montreal (Place d'Armes, MTLaTABLE)",
    "sentiment_polarity": 0.0,
    "sentiment_subjectivity": 0.0,
    "category": "other",
    "vader_compound": 0.0,
    "vader_pos": 0.0,
    "vader_neg": 0.0,
    "sentiment_adjusted": 0.0,
    "topic": "Topic 1: sep, 27, turned, birthday",
    "life_stage": "Return with the Elixir"
  },
  {
    "year": 2024,
    "milestone": "Norway cruise (Alesund, Akureyri, Iceland Sky Lagoon)",
    "sentiment_polarity": 0.0,
    "sentiment_subjectivity": 0.0,
    "category": "travel",
    "vader_compound": 0.0,
    "vader_pos": 0.0,
    "vader_neg": 0.0,
    "sentiment_adjusted": 0.05,
    "topic": "Topic 4: cruise, croatia, years, 10",
    "life_stage": "Return with the Elixir"
  },
  {
    "year": 2024,
    "milestone": "Spain trip (Lisbon, Madrid)",
    "sentiment_polarity": 0.0,
    "sentiment_subjectivity": 0.0,
    "category": "travel",
    "vader_compound": 0.0,
    "vader_pos": 0.0,
    "vader_neg": 0.0,
    "sentiment_adjusted": 0.05,
    "topic": "Topic 3: trip, ski, 000, road",
    "life_stage": "Return with the Elixir"
  },
  {
    "year": 2024,
    "milestone": "Toronto (CN Tower 1,815 ft, Niagara Falls)",
    "sentiment_polarity": 0.0,
    "sentiment_subjectivity": 0.0,
    "category": "other",
    "vader_compound": 0.0,
    "vader_pos": 0.0,
    "vader_neg": 0.0,
    "sentiment_adjusted": 0.0,
    "topic": "Topic 3: trip, ski, 000, road",
    "life_stage": "Return with the Elixir"
  },
  {
    "year": 2024,
    "milestone": "Wicked on Broadway",
    "sentiment_polarity": 0.0,
    "sentiment_subjectivity": 0.0,
    "category": "entertainment",
    "vader_compound": -0.527,
    "vader_pos": 0.0,
    "vader_neg": 0.63,
    "sentiment_adjusted": -0.527,
    "topic": "Topic 2: year, comedian, anniversary, ecd",
    "life_stage": "Return with the Elixir"
  },
  {
    "year": 2025,
    "milestone": "20th Anniversary celebration",
    "sentiment_polarity": 0.0,
    "sentiment_subjectivity": 0.0,
    "category": "relationship",
    "vader_compound": 0.0,
    "vader_pos": 0.0,
    "vader_neg": 0.0,
    "sentiment_adjusted": 0.0,
    "topic": "Topic 2: year, comedian, anniversary, ecd",
    "life_stage": "Return with the Elixir"
  },
  {
    "year": 2025,
    "milestone": "4,000-mile Midwest road trip (16 states: Rushmore, Devils Tower, Gateway Arch, Badlands)",
    "sentiment_polarity": 0.0,
    "sentiment_subjectivity": 0.0,
    "category": "travel",
    "vader_compound": -0.572,
    "vader_pos": 0.0,
    "vader_neg": 0.252,
    "sentiment_adjusted": -0.522,
    "topic": "Topic 3: trip, ski, 000, road",
    "life_stage": "Return with the Elixir"
  },
  {
    "year": 2025,
    "milestone": "Anniversary XX celebration \u2014 20-year Timeline milestone (Sep 27)",
    "sentiment_polarity": 0.0,
    "sentiment_subjectivity": 0.0,
    "category": "other",
    "vader_compound": 0.0,
    "vader_pos": 0.0,
    "vader_neg": 0.0,
    "sentiment_adjusted": 0.0,
    "topic": "Topic 2: year, comedian, anniversary, ecd",
    "life_stage": "Return with the Elixir"
  },
  {
    "year": 2025,
    "milestone": "Coastal cruise getaway (Sep 28 - Oct 5)",
    "sentiment_polarity": 0.0,
    "sentiment_subjectivity": 0.0,
    "category": "other",
    "vader_compound": 0.0,
    "vader_pos": 0.0,
    "vader_neg": 0.0,
    "sentiment_adjusted": 0.0,
    "topic": "Topic 4: cruise, croatia, years, 10",
    "life_stage": "Return with the Elixir"
  },
  {
    "year": 2025,
    "milestone": "ECD Bowl Weekend (57 people, $1,700+ raised)",
    "sentiment_polarity": 0.0,
    "sentiment_subjectivity": 0.0,
    "category": "ecd",
    "vader_compound": 0.0,
    "vader_pos": 0.0,
    "vader_neg": 0.0,
    "sentiment_adjusted": 0.0,
    "topic": "Topic 2: year, comedian, anniversary, ecd",
    "life_stage": "Return with the Elixir"
  },
  {
    "year": 2025,
    "milestone": "Emotional crisis and relationship transition (late May-early June)",
    "sentiment_polarity": -0.15,
    "sentiment_subjectivity": 0.625,
    "category": "other",
    "vader_compound": -0.542,
    "vader_pos": 0.137,
    "vader_neg": 0.35,
    "sentiment_adjusted": -0.542,
    "topic": "Topic 5: dec, 15, 18, 12",
    "life_stage": "Return with the Elixir"
  },
  {
    "year": 2025,
    "milestone": "Executive Director promotion (passed NJ certification)",
    "sentiment_polarity": 0.0,
    "sentiment_subjectivity": 0.0,
    "category": "career",
    "vader_compound": 0.0,
    "vader_pos": 0.0,
    "vader_neg": 0.0,
    "sentiment_adjusted": 0.0,
    "topic": "Topic 8: jul, 29, birthday, married",
    "life_stage": "Return with the Elixir"
  },
  {
    "year": 2025,
    "milestone": "Five Boro Bike Tour medal finish",
    "sentiment_polarity": 0.0,
    "sentiment_subjectivity": 0.0,
    "category": "sports",
    "vader_compound": 0.477,
    "vader_pos": 0.383,
    "vader_neg": 0.0,
    "sentiment_adjusted": 0.477,
    "topic": "Topic 7: aug, 16, dodgeball, 21",
    "life_stage": "Return with the Elixir"
  },
  {
    "year": 2025,
    "milestone": "Influenza confirmed (February)",
    "sentiment_polarity": 0.4,
    "sentiment_subjectivity": 1.0,
    "category": "other",
    "vader_compound": 0.0,
    "vader_pos": 0.0,
    "vader_neg": 0.0,
    "sentiment_adjusted": 0.0,
    "topic": "Topic 7: aug, 16, dodgeball, 21",
    "life_stage": "Return with the Elixir"
  },
  {
    "year": 2025,
    "milestone": "Mother's 70th birthday",
    "sentiment_polarity": 0.0,
    "sentiment_subjectivity": 0.0,
    "category": "family",
    "vader_compound": 0.0,
    "vader_pos": 0.0,
    "vader_neg": 0.0,
    "sentiment_adjusted": 0.0,
    "topic": "Topic 8: jul, 29, birthday, married",
    "life_stage": "Return with the Elixir"
  },
  {
    "year": 2025,
    "milestone": "NJ Executive Director certification passed",
    "sentiment_polarity": 0.0,
    "sentiment_subjectivity": 0.0,
    "category": "other",
    "vader_compound": 0.0,
    "vader_pos": 0.0,
    "vader_neg": 0.0,
    "sentiment_adjusted": 0.0,
    "topic": "Topic 8: jul, 29, birthday, married",
    "life_stage": "Return with the Elixir"
  },
  {
    "year": 2026,
    "milestone": "Japan trip (booked \u2014 Tokyo bound)",
    "sentiment_polarity": 0.0,
    "sentiment_subjectivity": 0.0,
    "category": "travel",
    "vader_compound": 0.0,
    "vader_pos": 0.0,
    "vader_neg": 0.0,
    "sentiment_adjusted": 0.05,
    "topic": "Topic 3: trip, ski, 000, road",
    "life_stage": "Return with the Elixir"
  }
]