[
  {
    "year": 2004,
    "avg_grade_level": 14.25,
    "avg_word_count": 8.0,
    "vocabulary_richness": 1.0,
    "avg_sentence_length": 16.0,
    "total_words": 16,
    "dominant_topic": "Topic 8: jul, 29, birthday, married",
    "topic_diversity": 0.40462490280573904,
    "emotional_range": 0.875,
    "quote_density": 0.0,
    "thematic_coherence": 0.5502264720873042
  },
  {
    "year": 2006,
    "avg_grade_level": 15.15,
    "avg_word_count": 11.0,
    "vocabulary_richness": 0.9091,
    "avg_sentence_length": 31.0,
    "total_words": 33,
    "dominant_topic": "Topic 5: dec, 15, 18, 12",
    "topic_diversity": 1.4274230796988316,
    "emotional_range": 0.0,
    "quote_density": 0.0,
    "thematic_coherence": 0.39490749179663753
  },
  {
    "year": 2007,
    "avg_grade_level": 16.81,
    "avg_word_count": 9.5,
    "vocabulary_richness": 0.7385,
    "avg_sentence_length": 36.0,
    "total_words": 218,
    "dominant_topic": "Topic 8: jul, 29, birthday, married",
    "topic_diversity": 2.438500267879636,
    "emotional_range": 0.4404,
    "quote_density": 0.42857142857142855,
    "thematic_coherence": 0.44045233878886714
  },
  {
    "year": 2008,
    "avg_grade_level": 8.15,
    "avg_word_count": 10.5,
    "vocabulary_richness": 0.7449,
    "avg_sentence_length": 14.3,
    "total_words": 345,
    "dominant_topic": "Topic 2: year, comedian, anniversary, ecd",
    "topic_diversity": 1.9629458516016858,
    "emotional_range": 0.9171,
    "quote_density": 1.2857142857142858,
    "thematic_coherence": 0.6241360047836484
  },
  {
    "year": 2009,
    "avg_grade_level": 16.24,
    "avg_word_count": 11.9,
    "vocabulary_richness": 0.7156,
    "avg_sentence_length": 36.6,
    "total_words": 334,
    "dominant_topic": "Topic 7: aug, 16, dodgeball, 21",
    "topic_diversity": 2.624357596501496,
    "emotional_range": 0.9981,
    "quote_density": 0.6428571428571429,
    "thematic_coherence": 0.7291543195699002
  },
  {
    "year": 2010,
    "avg_grade_level": 14.0,
    "avg_word_count": 8.9,
    "vocabulary_richness": 0.728,
    "avg_sentence_length": 41.0,
    "total_words": 125,
    "dominant_topic": "Topic 8: jul, 29, birthday, married",
    "topic_diversity": 2.439968172749977,
    "emotional_range": 0.8415,
    "quote_density": 0.1,
    "thematic_coherence": 0.6688869526750882
  },
  {
    "year": 2011,
    "avg_grade_level": 14.0,
    "avg_word_count": 7.6,
    "vocabulary_richness": 0.814,
    "avg_sentence_length": 127.0,
    "total_words": 129,
    "dominant_topic": "Topic 7: aug, 16, dodgeball, 21",
    "topic_diversity": 2.461521567473679,
    "emotional_range": 0.9978,
    "quote_density": 0.08333333333333333,
    "thematic_coherence": 0.5948715037140242
  },
  {
    "year": 2012,
    "avg_grade_level": 30.64,
    "avg_word_count": 7.1,
    "vocabulary_richness": 0.9155,
    "avg_sentence_length": 69.0,
    "total_words": 71,
    "dominant_topic": "Topic 6: wwe, event, oct, mar",
    "topic_diversity": 2.616982244663133,
    "emotional_range": 0.2,
    "quote_density": 0.0,
    "thematic_coherence": 0.6848098909293259,
    "grade_level": 18
  },
  {
    "year": 2013,
    "avg_grade_level": 13.1,
    "avg_word_count": 10.5,
    "vocabulary_richness": 0.7414,
    "avg_sentence_length": 28.4,
    "total_words": 232,
    "dominant_topic": "Topic 6: wwe, event, oct, mar",
    "topic_diversity": 2.950364061121124,
    "emotional_range": 1.0123,
    "quote_density": 0.6666666666666666,
    "thematic_coherence": 0.7794983813472297
  },
  {
    "year": 2014,
    "avg_grade_level": 7.77,
    "avg_word_count": 9.4,
    "vocabulary_richness": 0.8556,
    "avg_sentence_length": 18.1,
    "total_words": 187,
    "dominant_topic": "Topic 5: dec, 15, 18, 12",
    "topic_diversity": 2.4945851143694835,
    "emotional_range": 1.4067,
    "quote_density": 0.8,
    "thematic_coherence": 0.7447577751457409
  },
  {
    "year": 2015,
    "avg_grade_level": 22.9,
    "avg_word_count": 10.0,
    "vocabulary_richness": 0.85,
    "avg_sentence_length": 58.0,
    "total_words": 60,
    "dominant_topic": "Topic 2: year, comedian, anniversary, ecd",
    "topic_diversity": 1.7519498237816493,
    "emotional_range": 1.2227999999999999,
    "quote_density": 0.25,
    "thematic_coherence": 0.8351678019673885,
    "grade_level": 18
  },
  {
    "year": 2016,
    "avg_grade_level": 10.15,
    "avg_word_count": 6.7,
    "vocabulary_richness": 0.7297,
    "avg_sentence_length": 14.6,
    "total_words": 74,
    "dominant_topic": "Topic 2: year, comedian, anniversary, ecd",
    "topic_diversity": 2.074673041439229,
    "emotional_range": 0.6369,
    "quote_density": 0.2857142857142857,
    "thematic_coherence": 0.760308551003129
  },
  {
    "year": 2017,
    "avg_grade_level": 13.41,
    "avg_word_count": 7.2,
    "vocabulary_richness": 0.8862,
    "avg_sentence_length": 23.6,
    "total_words": 123,
    "dominant_topic": "Topic 5: dec, 15, 18, 12",
    "topic_diversity": 2.737248643553363,
    "emotional_range": 1.0034,
    "quote_density": 0.23076923076923078,
    "thematic_coherence": 0.7391351150086402
  },
  {
    "year": 2018,
    "avg_grade_level": 14.55,
    "avg_word_count": 8.1,
    "vocabulary_richness": 0.7528,
    "avg_sentence_length": 28.8,
    "total_words": 178,
    "dominant_topic": "Topic 7: aug, 16, dodgeball, 21",
    "topic_diversity": 2.6065386647574673,
    "emotional_range": 0.7506,
    "quote_density": 0.15384615384615385,
    "thematic_coherence": 0.79596633823779
  },
  {
    "year": 2019,
    "avg_grade_level": 19.2,
    "avg_word_count": 7.7,
    "vocabulary_richness": 0.7892,
    "avg_sentence_length": 45.2,
    "total_words": 185,
    "dominant_topic": "Topic 5: dec, 15, 18, 12",
    "topic_diversity": 2.4689143666733004,
    "emotional_range": 1.3494000000000002,
    "quote_density": 0.4,
    "thematic_coherence": 0.76972787504593
  },
  {
    "year": 2020,
    "avg_grade_level": 14.46,
    "avg_word_count": 9.4,
    "vocabulary_richness": 0.8434,
    "avg_sentence_length": 31.7,
    "total_words": 198,
    "dominant_topic": "Topic 5: dec, 15, 18, 12",
    "topic_diversity": 2.5226664455602865,
    "emotional_range": 0.9285999999999999,
    "quote_density": 0.7272727272727273,
    "thematic_coherence": 0.7810834302785571
  },
  {
    "year": 2021,
    "avg_grade_level": 8.12,
    "avg_word_count": 7.0,
    "vocabulary_richness": 0.787,
    "avg_sentence_length": 12.6,
    "total_words": 216,
    "dominant_topic": "Topic 5: dec, 15, 18, 12",
    "topic_diversity": 2.799529954852642,
    "emotional_range": 1.248,
    "quote_density": 0.25,
    "thematic_coherence": 0.6887300653834092
  },
  {
    "year": 2022,
    "avg_grade_level": 34.32,
    "avg_word_count": 4.9,
    "vocabulary_richness": 0.9459,
    "avg_sentence_length": 74.0,
    "total_words": 74,
    "dominant_topic": "Topic 3: trip, ski, 000, road",
    "topic_diversity": 2.2339705879297687,
    "emotional_range": 0.5423,
    "quote_density": 0.0,
    "thematic_coherence": 0.40462028765894986,
    "grade_level": 18
  },
  {
    "year": 2023,
    "avg_grade_level": 27.96,
    "avg_word_count": 8.3,
    "vocabulary_richness": 0.8966,
    "avg_sentence_length": 57.0,
    "total_words": 58,
    "dominant_topic": "Topic 2: year, comedian, anniversary, ecd",
    "topic_diversity": 1.5497214927203775,
    "emotional_range": 0.7506,
    "quote_density": 0.16666666666666666,
    "thematic_coherence": 0.22332428262848086,
    "grade_level": 18
  },
  {
    "year": 2024,
    "avg_grade_level": 28.65,
    "avg_word_count": 5.3,
    "vocabulary_richness": 0.9531,
    "avg_sentence_length": 63.0,
    "total_words": 64,
    "dominant_topic": "Topic 3: trip, ski, 000, road",
    "topic_diversity": 2.3810409695409125,
    "emotional_range": 0.5267,
    "quote_density": 0.0,
    "thematic_coherence": 0.43184727848216636,
    "grade_level": 18
  },
  {
    "year": 2025,
    "avg_grade_level": 35.05,
    "avg_word_count": 6.4,
    "vocabulary_richness": 0.9143,
    "avg_sentence_length": 68.0,
    "total_words": 70,
    "dominant_topic": "Topic 1: sep, 27, turned, birthday",
    "topic_diversity": 2.771607438230985,
    "emotional_range": 1.0486,
    "quote_density": 0.0,
    "thematic_coherence": 0.4860920374603786,
    "grade_level": 18
  }
]